Workbook

Sheet output_file_it3
A1: Doi | B1: DB | C1: Title | D1: Abstract | E1: keywords | F1: Terms category 1 | G1: Terms category 2 | H1: Terms 1 | I1: Terms 2 | J1: Length T1 | K1: Length T2
A2: /doi/10.1145/3590003.3590014 | B2: ACM | C2: Garment Metaverse: Parametric Digital Human and Dynamic Scene Try-on | D2: As a new concept, the metaverse has been widely concerned by the industry, academia, media and the public. Many domestic and foreign companies have also set up in the field of the metaverse. The traditional 2D and 3D virtual fitting has not achieved breakthrough and development because of the technical problems of authenticity and timeliness. With this in mind, we developed a virtual fitting system based on the metaverse community, which includes two modules: parameterized virtual digital human modeling and multi-scene and multi-action fitting. The system realizes the construction of individualized virtual digital person. As the medium between the metaverse clothing community and the real world, it is used to achieve multi-category dynamic fitting display actions in the meta-universe clothing community platform for multi-category scenes. The system integrates the high simulation and synchronization of the metaverse with the virtual fitting system, to break the barriers of traditional virtual fitting technology and realize the combination of the garment industry and the metaverse. The experimental results show that the system can realize the construction of virtual digital human in 2.1ms at the fastest and realize the dynamic display of multi-action and multi-scene fitting. | E2: 3D face reconstruction, Digital human, Metaverse, Virtual try-on | F2: 900 - No match | G2: 900 - No match | H2: [] | I2: [] | J2: =+LEN(H2) -> 2 | K2: =+LEN(I2) -> 2
A3: /doi/10.1109/MODELS.2017.28 | B3: ACM | C3: DREAMS toolchain: model-driven engineering of mixed-criticality systems | D3: Mixed-criticality systems (MCS) aim at boosting the integration density in safety-critical systems, resulting into efficient systems, while simultaneously providing increased performance. The DREAMS project provides a cross-domain architectural style for MCS based on networked, virtualized multi-cores controlled by hierarchical resource managers. However, the availability of a platform is only one side of the coin: deploying mixed-critical applications to shared resources typically requires design-time configurations (e.g., to ensure real-time constraints or separation constraints mandated by safety regulations). These configurations are the outcome of complex optimization problems which are intractable in a manual process that also hardly can guarantee the consistency of all deployable artefacts nor their traceability to the requirements. However, existing toolchains lack support for MCS integration, and particularly DREAMS' advanced platform capabilities. | E3: design space exploration, mixed-criticalitity systems, model-driven engineering, product-lines, resource management, safety | F3: 900 - No match | G3: 900 - No match | H3: [] | I3: [] | J3: =+LEN(H3) -> 2 | K3: =+LEN(I3) -> 2
A4: /doi/10.1145/3626772.3657818 | B4: ACM | C4: AutoDCS: Automated Decision Chain Selection in Deep Recommender Systems | D4: Multi-behavior recommender systems (MBRS) have been commonly deployed on real-world industrial platforms for their superior advantages in understanding user preferences and mitigating data sparsity. However, the cascade graph modeling paradigm adopted in mainstream MBRS usually assumes that users will refer to all types of behavioral knowledge they have when making decisions about target behaviors, i.e., use all types of behavioral interactions indiscriminately when modeling and predicting target behaviors for each user. We call this a full decision chain constraint and argue that it may be too strict by ignoring that different types of behavioral knowledge have varying importance for different users. In this paper, we propose a novel automated decision chain selection (AutoDCS) framework to relax this constraint, which can consider each user's unique decision dependencies and select a reasonable set of behavioral knowledge to activate for the prediction of target behavior. Specifically, AutoDCS first integrates some existing MBRS methods in a base cascade module to obtain a set of behavior-aware embeddings. Then, a bilateral matching gating mechanism is used to select an exclusive set of behaviors for the current user-item pair to form a decision chain, and the corresponding behavior-augmented embeddings are selectively activated. Subsequently, AutoDCS combines the behavior-augmented and original behavior-aware embeddings to predict the target behavior. Finally, we evaluate AutoDCS and demonstrate its effectiveness through experiments over four public multi-behavior benchmarks. | E4: bilateral matching gate, decision chain selection, deep recommender system, multi-behavior learning | F4: 3 - Modified acrs | G4: 900 - No match | H4: ['MBRS'] | I4: [] | J4: =+LEN(H4) -> 8 | K4: =+LEN(I4) -> 2
A5: /doi/10.1145/3458864.3466868 | B5: ACM | C5: A real-time experimentation platform for sub-6 GHz and millimeter-wave MIMO systems | D5: The performance of wireless communication systems is evolving rapidly, making it difficult to build experimentation platforms that meet the hardware requirements of new standards. The bandwidth of current systems ranges from 160 MHz for IEEE 802.11ac/ax to 2 GHz for Millimeter-Wave (mm-wave) IEEE 802.11ad/ay, and they support up to 8 spatial MIMO streams. Mobile 5G and beyond systems have a similarly diverse set of requirements. | E5: FPGA, MIMO, millimeter wave, multi-band, phased antenna array, testbed | F5: 900 - No match | G5: 900 - No match | H5: [] | I5: [] | J5: =+LEN(H5) -> 2 | K5: =+LEN(I5) -> 2
A6: /doi/10.1145/3660043.3660053 | B6: ACM | C6: The Research on â€œVirtual-real Integration, Multi-level Progressiveâ€ Practical Teaching: Take the Course â€œComprehensive Design and Production of the Internet of Things (Perception Layer)â€ as An Example | D6: The course "Comprehensive Design and Production of the Internet of Things (Perception Layer)" takes the information acquisition system of the perception Layer of the Internet of Things as the design direction, and completes the design and production of the system, including the construction of hardware circuits and the design of control programs. It is a typical offline practical training course. In order to solve the key points of practical courses, such as low classroom utilization, students â€œfishing in troubled watersâ€, and offline suspension of classes in epidemic areas, this case has been designed in teaching content, teaching design, and experimental methods to develop a â€œvirtual-real integration, multi-level progressiveâ€ teaching model. In terms of teaching content and teaching design, through the route of â€œbasic knowledge â†’ module practice â†’ project actual combatâ€, and with a more detailed and reasonable evaluation system, students can be guided from shallow to deep, easy first and then difficult, from simple to complex to learn and gradually improve, so as to stimulate students' interest in learning and improve practical innovation ability; In terms of experimental teaching methods, the Tinkercad simulation platform is introduced to implement a â€œvirtual-real fusionâ€ teaching plan. Students can combine the simulation platform with physical production to meet the teaching requirements of â€œsuspension of classes and non-stop learningâ€ during the epidemic, get rid of the limitations of physical components, and ensure that students can complete the design of the circuit and the debugging of the program anyway, and the teaching goals of the course can be achieved. | F6: 900 - No match | G6: 900 - No match | H6: [] | I6: [] | J6: =+LEN(H6) -> 2 | K6: =+LEN(I6) -> 2
A7: /doi/10.1145/3569470 | B7: ACM | C7: TransFloor: Transparent Floor Localization for Crowdsourcing Instant Delivery | D7: Smart on-demand delivery services require accurate indoor localization to enhance the system-human synergy experience of couriers in complex multi-story malls and platform construction. Floor localization is an essential part of indoor positioning, which can provide floor/altitude data support for upper-level 3D indoor navigation services (e.g., delivery route planning) to improve delivery efficiency and optimize order dispatching strategies. We argue that due to label dependence and device dependence, the existing floor localization methods cannot be flexibly deployed on a large scale in numerous multi-story malls across the country, nor can they apply to all couriers/users on the platform. This paper proposes a novel self-evolving and user-transparent floor localization system named TransFloor, based on crowdsourcing delivery data (e.g., order status and sensors data) without additional label investment and specialized equipment constraints. TransFloor consists of an unsupervised barometer-based module--IOD-TKPD and an NLP-inspired Wi-Fi-based module--Wifi2Vec, and Self-Labeling is a perfect bridge between both to completely achieve label-free and device-independent floor positioning. In addition, TransFloor is designed as a lightweight plugin embedded into the platform without refactoring the existing architecture, and it has been deployed nationwide to adaptively launch real-time accurate 3D/floor positioning services for numerous crowdsourcing couriers. We evaluate TransFloor on real-world records from an instant delivery platform (involving 672,282 orders, 7,390 couriers, and 6,206 merchants in 388 malls during two months). It can achieve an average accuracy of 94.61% and demonstrate good robustness to device heterogeneity and adaptive durability, outperforming existing state-of-the-art methods. Crucially, it can effectively improve user satisfaction and reduce overdue delivery by providing accurate floor navigation information in complex multi-story malls. As a case study, the platform reduces erroneous order scheduling by 60% and overdue delivery by 2.7%, and increases delivery efficiency by reducing courier arrival time by 12.27 seconds accounting for 7.29%. We believe that the key ideas of TransFloor can be extended to other crowdsourcing scenarios for the public further. | E7: 3D indoor localization, Crowdsourcing, Floor localization, Instant delivery | F7: 900 - No match | G7: 900 - No match | H7: [] | I7: [] | J7: =+LEN(H7) -> 2 | K7: =+LEN(I7) -> 2
A8: /doi/10.1145/3637528.3671612 | B8: ACM | C8: ADSNet: Cross-Domain LTV Prediction with an Adaptive Siamese Network in Advertising | D8: Advertising platforms have evolved in estimating Lifetime Value (LTV) to better align with advertisers' true performance metric which considers cumulative sum of purchases a customer contributes over a period. Accurate LTV estimation is crucial for the precision of the advertising system and the effectiveness of advertisements. However, the sparsity of real-world LTV data presents a significant challenge to LTV predictive model(i.e., pLTV), severely limiting the their capabilities. Therefore, we propose to utilize external data, in addition to the internal data of advertising platform, to expand the size of purchase samples and enhance the LTV prediction model of the advertising platform. To tackle the issue of data distribution shift between internal and external platforms, we introduce an Adaptive Difference Siamese Network (ADSNet), which employs cross-domain transfer learning to prevent negative transfer. Specifically, ADSNet is designed to learn information that is beneficial to the target domain. We introduce a gain evaluation strategy to calculate information gain, aiding the model in learning helpful information for the target domain and providing the ability to reject noisy samples, thus avoiding negative transfer. Additionally, we also design a Domain Adaptation Module as a bridge to connect different domains, reduce the distribution distance between them, and enhance the consistency of representation space distribution. We conduct extensive offline experiments and online A/B tests on a real advertising platform. Our proposed ADSNet method outperforms other methods, improving GINI by 2%. The ablation study highlights the importance of the gain evaluation strategy in negative gain sample rejection and improving model performance. Additionally, ADSNet significantly improves long-tail prediction. The online A/B tests confirm ADSNet's efficacy, increasing online LTV by 3.47% and GMV by 3.89%. | E8: adaptive cross-domain transfer learning, computational advertising, lifetime value prediction | F8: 900 - No match | G8: 900 - No match | H8: [] | I8: [] | J8: =+LEN(H8) -> 2 | K8: =+LEN(I8) -> 2
A9: /doi/10.1145/3592609 | B9: ACM | C9: Multi-criteria Optimization of Real-time DAGs on Heterogeneous Platforms under P-EDF | D9: This article tackles the problem of optimal placement of complex real-time embedded applications on heterogeneous platforms. Applications are composed of directed acyclic graphs of tasks, with each directed-acyclic-graph (DAG) having a minimum inter-arrival period for its activation requests and an end-to-end deadline within which all of the computations need to terminate since each activation. The platforms of interest are heterogeneous power-aware multi-core platforms with Dynamic Voltage and Frequency Scaling (DVFS) capabilities, including big.LITTLE Arm architectures and platforms with GPU or FPGA hardware accelerators with Dynamic Partial Reconfiguration capabilities. Tasks can be deployed on CPUs using partitioned EDF-based scheduling. Additionally, some of the tasks may have an alternate implementation available for one of the accelerators on the target platform, which are assumed to serve requests in non-preemptive FIFO order. The system can be optimized by minimizing power consumption, respecting precise timing constraints, maximizing the applicationsâ€™ slack, respecting given power consumption constraints, or even a combination of these, in a multi-objective formulation. | E9: End-to-end timing requirements, energy efficiency, DVFS, software-to-hardware mapping, mixed-integer quadratic constraint programming, heuristic optimization, Linux kernel, SCHED_DEADLINE | F9: 900 - No match | G9: 900 - No match | H9: [] | I9: [] | J9: =+LEN(H9) -> 2 | K9: =+LEN(I9) -> 2
A10: /doi/10.1145/3583780.3614978 | B10: ACM | C10: Multi-modal Mixture of Experts Represetation Learning for Sequential Recommendation | D10: Within online platforms, it is critical to capture the dynamic user preference from the sequential interaction behaviors for making accurate recommendation over time. Recently, significant progress has been made in sequential recommendation with deep learning. However, existing neural sequential recommender often suffer from the data sparsity issue in real-world applications. | E10: multi-modal recommendation, user behavior modeling | F10: 900 - No match | G10: 900 - No match | H10: [] | I10: [] | J10: =+LEN(H10) -> 2 | K10: =+LEN(I10) -> 2
A11: /doi/10.1145/3589334.3645697 | B11: ACM | C11: Is It Safe to Share Your Files? An Empirical Security Analysis of Google Workspace | D11: The increasing demand for remote work and virtual interactions has heightened the usage of business collaboration platforms~(BCPs), with Google Workspace as a prominent example. These platforms enhance team collaboration by integrating Google Docs, Slides, Calendar, and feature-rich third-party applications (add-ons). However, such integration of multiple users and entities has inadvertently introduced new and complex attack surfaces, elevating security and privacy risks in resource management to unprecedented levels. In this study, we conduct a systematic study on the effectiveness of the cross-entity resource management in Google Workspace, the most popular BCP. Our study unveils the access control enforcement in real-world BCPs for the first time. Based on this, we formulate the attack surfaces inherent in BCPs and conduct a comprehensive assessment, pinpointing three vulnerability types leading to distinct attacks. An analysis of 4,732 marketplace add-ons reveals that approximately 70% are potentially vulnerable to these attacks. We propose robust countermeasures to improve BCP security, urging immediate action and setting a foundation for future research. | E11: Google workspace, add-ons, security vulnerabilities, sharing | F11: 900 - No match | G11: 2 - Complete terms | H11: [] | I11: ['collaboration'] | J11: =+LEN(H11) -> 2 | K11: =+LEN(I11) -> 17
A12: /doi/10.1145/3632953 | B12: ACM | C12: Fine-grain Quantitative Analysis of Demand Paging in Unified Virtual Memory | D12: The abstraction of a shared memory space over separate CPU and GPU memory domains has eased the burden of portability for many HPC codebases. However, users pay for ease of use provided by system-managed memory with a moderate-to-high performance overhead. NVIDIA Unified Virtual Memory (UVM) is currently the primary real-world implementation of such abstraction and offers a functionally equivalent testbed for in-depth performance study for both UVM and future Linux Heterogeneous Memory Management (HMM) compatible systems. The continued advocacy for UVM and HMM motivates improvement of the underlying system. We focus on UVM-based systems and investigate the root causes of UVM overhead, a non-trivial task due to complex interactions of multiple hardware and software constituents and the desired cost granularity. | E12: Unified Virtual Memory, Heterogeneous Memory Management, Virtual Memory, GPGPU, Accelerated Computing | F12: 900 - No match | G12: 900 - No match | H12: [] | I12: [] | J12: =+LEN(H12) -> 2 | K12: =+LEN(I12) -> 2
A13: /doi/10.1145/3495018.3495469 | B13: ACM | C13: Development of Digital Signal Processing Simulation Platform Based on DSP and FPGA Cooperative Processing Technology | D13: As digital signals are widely used in various fields such as technology, communications, and software, the digital signal processing platform is part of a long-base tracking system used to perform signal detection and placement. Compared with the traditional analog signal processing platform based on the digital signal processing simulation platform based on DSP and FPGA co-processing technology, the digital signal processing system not only has more advantages in terms of sensitivity and accuracy, but also has lower development cost and Wider application environment requirements. DSP multi-core board and DSP core, FPGA core signal receiving board and back-end circuit design have very important significance. The function of software design is to collect data from the FPGA board and transmit the data to the multi-core DSP through the PCIE bus. DSP and FPGA provide great help for the design of hardware installation. Pay special attention to the circuit design of multi-core DSP board with multi-core DSP, FPGA nuclear signal receiving board and backplane. The function that the software design realizes is FPGA board card gathers the data signal. This paper analyzes the relevant characteristics and theoretical knowledge of DSP and FPGA co-processing technology, transmits data to the multi-core DSP board through the PCIE bus, completes the relevant detection of multi-channel signals on the multi-core DSP board, and realizes the development of a digital signal processing simulation platform. The final result of the research shows that when the real running time is 1523ms, the virtual simulation time is 123ms. When the real running time increases, the virtual simulation time also increases, showing a proportional relationship. The virtual simulation time has a shorter and faster running time. | F13: 900 - No match | G13: 900 - No match | H13: [] | I13: [] | J13: =+LEN(H13) -> 2 | K13: =+LEN(I13) -> 2
A14: /doi/10.1145/3539618.3592018 | B14: ACM | C14: MDDL: A Framework for Reinforcement Learning-based Position Allocation in Multi-Channel Feed | D14: Nowadays, the mainstream approach in position allocation system is to utilize a reinforcement learning model to allocate appropriate locations for items in various channels and then mix them into the feed. There are two types of data employed to train reinforcement learning (RL) model for position allocation, named strategy data and random data. Strategy data is collected from the current online model, it suffers from an imbalanced distribution of stateaction pairs, resulting in severe overestimation problems during training. On the other hand, random data offers a more uniform distribution of state-action pairs, but is challenging to obtain in industrial scenarios as it could negatively impact platform revenue and user experience due to random exploration. As the two types of data have different distributions, designing an effective strategy to leverage both types of data to enhance the efficacy of the RL model training has become a highly challenging problem. In this study, we propose a framework namedMulti-Distribution Data Learning (MDDL) to address the challenge of effectively utilizing both strategy and random data for training RL models on mixed multi-distribution data. Specifically, MDDL incorporates a novel imitation learning signal to mitigate overestimation problems in strategy data and maximizes the RL signal for random data to facilitate effective learning. In our experiments, we evaluated the proposed MDDL framework in a real-world position allocation system and demonstrated its superior performance compared to the previous baseline. MDDL has been fully deployed on the Meituan food delivery platform and currently serves over 300 million users. | E14: multi-distribution data learning, position allocation, reinforcement learning | F14: 900 - No match | G14: 900 - No match | H14: [] | I14: [] | J14: =+LEN(H14) -> 2 | K14: =+LEN(I14) -> 2
A15: /doi/10.1109/ASE56229.2023.00135 | B15: ACM | C15: An Empirical Study of Malicious Code In PyPI Ecosystem | D15: PyPI provides a convenient and accessible package management platform to developers, enabling them to quickly implement specific functions and improve work efficiency. However, the rapid development of the PyPI ecosystem has led to a severe problem of malicious package propagation. Malicious developers disguise malicious packages as normal, posing a significant security risk to end-users. | E15: PyPi ecosystem, package management, malicious code, mirror source, lifecycle portrait | F15: 900 - No match | G15: 900 - No match | H15: [] | I15: [] | J15: =+LEN(H15) -> 2 | K15: =+LEN(I15) -> 2
A16: /doi/10.14778/3476311.3476372 | B16: ACM | C16: Towards a polyglot framework for factorized ML | D16: Optimizing machine learning (ML) workloads on structured data is a key concern for data platforms. One class of optimizations called "factorized ML" helps reduce ML runtimes over multi-table datasets by pushing ML computations down through joins, avoiding the need to materialize such joins. The recent Morpheus system | F16: 900 - No match | G16: 900 - No match | H16: [] | I16: [] | J16: =+LEN(H16) -> 2 | K16: =+LEN(I16) -> 2
A17: /doi/10.1145/3459637.3482214 | B17: ACM | C17: Variational Cross-Network Embedding for Anonymized User Identity Linkage | D17: User identity linkage (UIL) task aims to infer the identical users between different social networks/platforms. Existing models leverage the labeled inter-linkages or high-quality user attributes to make predictions. Nevertheless, it is often difficult or even impossible to obtain such information in real-world applications. To this end, we in this paper focus on studying an Anonymized User Identity Linkage (AUIL) problem wherein neither labeled anchor users nor attributes are available. To handle such a practical and challenging task, we propose a novel and concise unsupervised embedding method, VCNE, by utilizing the network structural information. Concretely, considering the inherent properties of structural diversity in the AUIL problem, we introduce a variational cross-network embedding learning framework to jointly study the Gaussian embeddings instead of the existing deterministic embedding from the angle of vector space. The multi-facet experiments on both real-world and synthetic datasets demonstrate that VCNE not only outperforms all baselines to a large extent but also be more robust to the different-level diversities and sparsities of the networks. | E17: gaussian embedding, user identity linkage, variational auto-encoders | F17: 900 - No match | G17: 900 - No match | H17: [] | I17: [] | J17: =+LEN(H17) -> 2 | K17: =+LEN(I17) -> 2
A18: /doi/10.1145/3552326.3567487 | B18: ACM | C18: Making Dynamic Page Coalescing Effective on Virtualized Clouds | D18: Using huge pages has become a mainstream method to reduce address translation overhead for big memory workloads in modern computer systems. To create huge pages, system software usually uses page coalescing methods to dynamically combine contiguous base pages. Though page coalescing methods help effectively reduce address translation overhead on native systems, as the paper shows, their effectiveness is substantially undermined on virtualized platforms. | E18: cloud computing, memory management, virtualization, operating systems | F18: 900 - No match | G18: 900 - No match | H18: [] | I18: [] | J18: =+LEN(H18) -> 2 | K18: =+LEN(I18) -> 2
A19: /doi/10.1145/3485983.3494850 | B19: ACM | C19: OnSlicing: online end-to-end network slicing with reinforcement learning | D19: Network slicing allows mobile network operators to virtualize infrastructures and provide customized slices for supporting various use cases with heterogeneous requirements. Online deep reinforcement learning (DRL) has shown promising potential in solving network problems and eliminating the simulation-to-reality discrepancy. Optimizing cross-domain resources with online DRL is, however, challenging, as the random exploration of DRL violates the service level agreement (SLA) of slices and resource constraints of infrastructures. In this paper, we propose OnSlicing, an online end-to-end network slicing system, to achieve minimal resource usage while satisfying slices' SLA. OnSlicing allows individualized learning for each slice and maintains its SLA by using a novel constraint-aware policy update method and proactive baseline switching mechanism. OnSlicing complies with resource constraints of infrastructures by using a unique design of action modification in slices and parameter coordination in infrastructures. OnSlicing further mitigates the poor performance of online learning during the early learning stage by offline imitating a rule-based solution. Besides, we design four new domain managers to enable dynamic resource configuration in radio access, transport, core, and edge networks, respectively, at a timescale of subseconds. We implement OnSlicing on an end-to-end slicing testbed designed based on OpenAirInterface with both 4G LTE and 5G NR, OpenDayLight SDN platform, and OpenAir-CN core network. The experimental results show that OnSlicing achieves 61.3% usage reduction as compared to the rule-based solution and maintains nearly zero violation (0.06%) throughout the online learning phase. As online learning is converged, OnSlicing reduces 12.5% usage without any violations as compared to the state-of-the-art online DRL solution. | E19: end-to-end network slicing, online deep reinforcement learning, resource orchestration | F19: 900 - No match | G19: 900 - No match | H19: [] | I19: [] | J19: =+LEN(H19) -> 2 | K19: =+LEN(I19) -> 2
A20: /doi/10.1145/3580305.3599783 | B20: ACM | C20: BOSS: A Bilateral Occupational-Suitability-Aware Recommender System for Online Recruitment | D20: With the rapid development of online recruitment platforms, a variety of emerging recommendation services have been witnessed for benefiting both job seekers and recruiters. While many researchers have studied the problem of reciprocal recommendation in two- sided markets (e.g., marriage market and real estate market), there is still a lack of in-depth understanding of the bilateral occupational preferences of different participants in the online recruitment market. To this end, in this paper, we propose a Bilateral Occupational-Suitability-aware recommender System (BOSS) for online recruitment, in consideration of the reciprocal, bilateral, and sequential properties of realistic recruitment scenarios simultaneously. To be specific, in BOSS, we first propose a multi-group-based mixture-of-experts (MoE) module to independently learn the preference representations of job seekers and recruiters. Then, with a specially-designed multi-task learning module, BOSS can progressively model the action sequence of recruitment process through a bilateral probabilistic manner. As a result, the reciprocal recommendations can be efficiently implemented by leveraging the product of different action probabilities of job seekers and recruiters. Finally, we have conducted extensive experiments on 5 real-world large-scale datasets as well as the online environment. Both online A/B test and offline experimental results clearly validate that our recommender system BOSS can outperform other state-of-the-art baselines with a significant margin. | E20: multi-task learning, online recruitment, reciprocal recommender systems | F20: 900 - No match | G20: 900 - No match | H20: [] | I20: [] | J20: =+LEN(H20) -> 2 | K20: =+LEN(I20) -> 2
A21: /doi/10.1145/2466627.2466649 | B21: ACM | C21: Unwrapping virtual space through the myth of total cinema | D21: Visionary promises of a 3D virtual future are unfulfilled. Online 3D platforms such as VRML, Second Life, and Open Sim sought a 3D web of worlds and delivered, at best, mixed results. To understand the broad creative and cognitive challenges that drive the design of 3D virtual spaces, a cross-disciplinary design review of early cinema, a technical precursor, is needed. 150 years ago, a simulation oriented "Myth of a Total Cinema" guided and limited the development of the earliest films (Bazin 1958, Manovich 2001). Cinema was first seen as a realistic mirror world made of captured images. It would take decades for film makers to discover how to leave the myth and create montage, literally breaking a simulated reality apart in service to narrative. This text retraces the creative process of discovery, the tension between montage and the myth of total cinema, and then proposes a virtual design foundation stemming from an overlooked aspect of videogame theory. | E21: cinema, film, interactivity, narrative, simulation, total cinema, videogame, virtual world | F21: 3 - Modified acrs | G21: 900 - No match | H21: ['VRML'] | I21: [] | J21: =+LEN(H21) -> 8 | K21: =+LEN(I21) -> 2
A22: /doi/10.1145/2990299.2990311 | B22: ACM | C22: Design of an expandable real-time simulation (eRTS) platform for multi-level rapid prototyping | D22: A real-time simulation (RTS) platform is a critical design and verification for rapidly designing and testing electrical and computing hardware as well as embedded software employed in real-time embedded applications, including an autonomous electric vehicle (AEV). We have developed a wirelessly expandable real-time simulation (eRTS) platform for mixed-level rapid prototyping of an AEV system. The eRTS platform consisting of a microkernel-based multi-core RTS and multiple monolithic-kernel console units is interoperable to FPGA-based virtual prototypes and further expandable to the real prototype via wireless (IEEE 802.15.4). The multi-core RTS and multi-console units are interfaced with high-speed wire/wireless (IEEE 802.3u/802.11g) for both software-/hardware-in-the-loops (SIL/HIL) simulations. In particular, the eRTS provides a mixed-level of intuitively expandable HIL simulations with software models and virtual/real prototypes. The proposed eRTS platform swiftly handles different scale and complexity of AEV testing at various development stages while satisfying real-time constraints (i.e., 7 Î¼s resolutions and 0.3% HIL simulation error) of the AEV software models and virtual/real prototypes. | E22: autonomous electric vehicle, hardware-in-the-loop simulation, rapid prototyping, real-time simulator | F22: 900 - No match | G22: 900 - No match | H22: [] | I22: [] | J22: =+LEN(H22) -> 2 | K22: =+LEN(I22) -> 2
A23: /doi/10.1145/3678591 | B23: ACM | C23: HabitSense: A Privacy-Aware, AI-Enhanced Multimodal Wearable Platform for mHealth Applications | D23: Wearable cameras provide an objective method to visually confirm and automate the detection of health-risk behaviors such as smoking and overeating, which is critical for developing and testing adaptive treatment interventions. Despite the potential of wearable camera systems, adoption is hindered by inadequate clinician input in the design, user privacy concerns, and user burden. To address these barriers, we introduced HabitSense, an open-source1, multi-modal neck-worn platform developed with input from focus groups with clinicians (N=36) and user feedback from in-wild studies involving 105 participants over 35 days. Optimized for monitoring health-risk behaviors, the platform utilizes RGB, thermal, and inertial measurement unit sensors to detect eating and smoking events in real time. In a 7-day study involving 15 participants, HabitSense recorded 768 hours of footage, capturing 420.91 minutes of hand-to-mouth gestures associated with eating and smoking data crucial for training machine learning models, achieving a 92% F1-score in gesture recognition. To address privacy concerns, the platform records only during likely health-risk behavior events using SECURE, a smart activation algorithm. Additionally, HabitSense employs on-device obfuscation algorithms that selectively obfuscate the background during recording, maintaining individual privacy while leaving gestures related to health-risk behaviors unobfuscated. Our implementation of SECURE has resulted in a 48% reduction in storage needs and a 30% increase in battery life. This paper highlights the critical roles of clinician feedback, extensive field testing, and privacy-enhancing algorithms in developing an unobtrusive, lightweight, and reproducible wearable system that is both feasible and acceptable for monitoring health-risk behaviors in real-world settings. | E23: camera, eating, machine learning, multimodal, privacy, smoking, thermal, vision transformers, wearable | F23: 900 - No match | G23: 900 - No match | H23: [] | I23: [] | J23: =+LEN(H23) -> 2 | K23: =+LEN(I23) -> 2
A24: /doi/10.1145/3581783.3612568 | B24: ACM | C24: Modal-aware Bias Constrained Contrastive Learning for Multimodal Recommendation | D24: Multimodal recommendation system has been widely used in short video platform, e-commerce platform and news media. Multimodal data contains information such as product image and product text, which is often used as auxiliary signal to improve the effect of recommendation system significantly. In order to alleviate the problems of data sparsity and noise, some researchers construct data augmentation to use self-supervised learning to help model training. These methods have achieved certain results. However, most of the work is based on data augmentation in random ways, such as random masking and random perturbation. This random method is likely to lose important information and introduce new noise, resulting in biased augmentation data. Therefore, we propose a Modal-aware Bias Constrained Contrastive Learning method (BCCL) to solve the above problems. Specifically, BCCL introduces a bias-constrained data augmentation method to ensure the quality of augmentation samples. Then the multi-modal semantic information is modeled by the designed modal awareness module. Furthermore, we propose a information alignment module to improve the sparse modal feature learning of the model. We conducted a comprehensive experiment on three real-world data sets, and the experimental results showed that the proposed BCCL outperformed all the state-of-art methods. In-depth experiments have verified the effectiveness of our proposed modules. | E24: bias constraint, contrastive learning, multimodal recommendation | F24: 900 - No match | G24: 900 - No match | H24: [] | I24: [] | J24: =+LEN(H24) -> 2 | K24: =+LEN(I24) -> 2
A25: /doi/10.1145/3614419.3644022 | B25: ACM | C25: Exploring Local Music's Place in Global Streaming | D25: Music is intertwined with geography as part of the cultural fabric that transforms a physical space into what we consider a â€œplace." But in an increasingly online world, where musicâ€™s distribution has shifted massively towards digital streaming on global platforms, what role does geography now play in shaping peoplesâ€™ music consumption? Here, we employ a multi-part, mixed-methods study of â€œlocal" music, exploring its current definition as well as exploring its potential role in online music recommender systems. We present, first, findings from a qualitative study designed to identify themes in how listeners and artists defined local music across three international locations. Second, we present results of a quantitative analysis that operationalizes this definition and investigates the impact of surfacing local context in a real-world recommendation setting, conducted in one location. Together, our results illustrate that â€œlocal" continues to play a crucial role in shaping musicâ€™s enjoyment and represents an important mechanism for facilitating the discovery of lesser-known artists in online algorithmic recommendations. | E25: Computational Social Science, Globalization, Music, Recommender Systems | F25: 900 - No match | G25: 900 - No match | H25: [] | I25: [] | J25: =+LEN(H25) -> 2 | K25: =+LEN(I25) -> 2
A26: /doi/10.1145/2731186.2731188 | B26: ACM | C26: HSPT: Practical Implementation and Efficient Management of Embedded Shadow Page Tables for Cross-ISA System Virtual Machines | D26: Cross-ISA (Instruction Set Architecture) system-level virtual machine has a significant research and practical value. For example, several recently announced virtual smart phones for iOS which run smart phone applications on x86 based PCs are deployed on cross-ISA system level virtual machines. Also, for mobile device application development, by emulating the Android/ARM environment on the more powerful x86-64 platform, application development and debugging become more convenient and productive. However, the virtualization layer often incurs high performance overhead. The key overhead comes from memory virtualization where a guest virtual address (GVA) must go through multi-level address translation to become a host physical address (HPA). The Embedded Shadow Page Table (ESPT) approach has been proposed to effectively decrease this address translation cost. ESPT directly maps GVA to HPA, thus avoid the lengthy guest virtual to guest physical, guest physical to host virtual, and host virtual to host physical address translation. However, the original ESPT work has a few drawbacks. For example, its implementation relies on a loadable kernel module (LKM) to manage the shadow page table. Using LKMs is less desirable for system virtual machines due to portability, security and maintainability concerns. Our work proposes a different, yet more practical, implementation to address the shortcomings. Instead of relying on using LKMs, our approach adopts a shared memory mapping scheme to maintain the shadow page table (SPT) using only ''mmap'' system call. Furthermore, this work studies the support of SPT for multi-processing in greater details. It devices three different SPT organizations and evaluates their strength and weakness with standard and real Android applications on the system virtual machine which emulates the Android/ARM platform on x86-64 systems. | E26: cross-isa virtualization, embedded shadow page table, hosted shadow page table, hspt, loadable kernel module, memory virtualization, portability, practical implementation, security | F26: 3 - Modified acrs | G26: 900 - No match | H26: ['ARM'] | I26: [] | J26: =+LEN(H26) -> 7 | K26: =+LEN(I26) -> 2
A27: /doi/10.1145/3488560.3498527 | B27: ACM | C27: Contrastive Meta Learning with Behavior Multiplicity for Recommendation | D27: A well-informed recommendation framework could not only help users identify their interested items, but also benefit the revenue of various online platforms (e.g., e-commerce, social media). Traditional recommendation models usually assume that only a single type of interaction exists between user and item, and fail to model the multiplex user-item relationships from multi-typed user behavior data, such as page view, add-to-favourite and purchase. While some recent studies propose to capture the dependencies across different types of behaviors, two important challenges have been less explored: i) Dealing with the sparse supervision signal under target behaviors (e.g., purchase). ii) Capturing the personalized multi-behavior patterns with customized dependency modeling. To tackle the above challenges, we devise a new model CML, Contrastive Meta Learning (CML), to maintain dedicated cross-type behavior dependency for different users. In particular, we propose a multi-behavior contrastive learning framework to distill transferable knowledge across different types of behaviors via the constructed contrastive loss. In addition, to capture the diverse multi-behavior patterns, we design a contrastive meta network to encode the customized behavior heterogeneity for different users. Extensive experiments on three real-world datasets indicate that our method consistently outperforms various state-of-the-art recommendation methods. Our empirical studies further suggest that the contrastive meta learning paradigm offers great potential for capturing the behavior multiplicity in recommendation. We release our model implementation at: https://github.com/weiwei1206/CML.git. | E27: collaborative filtering, graph neural network, meta learning, multi-behavior recommendation, self-supervised learning | F27: 900 - No match | G27: 2 - Complete terms | H27: [] | I27: ['collaborative'] | J27: =+LEN(H27) -> 2 | K27: =+LEN(I27) -> 17
A28: /doi/10.1145/3678717.3691312 | B28: ACM | C28: Regional Features Conditioned Diffusion Models for 5G Network Traffic Generation | D28: The fifth-generation (5G) mobile network has significantly enhanced people's lives with faster internet speed and more reliable connections. However, there is still insufficient coverage of 5G networks worldwide, requiring telecom operators to deploy more base stations to meet the increasing demand for 5G's further commercialization. In this regard, a major challenge is understanding user network behaviors and traffic demands in target areas where 5G has not yet been deployed, which is crucial for developing a more efficient base station deployment strategy. Mobile traffic generation is a potential approach that enables operators to preemptively estimate user network demands in target areas, thereby specifying corresponding deployment strategies to enhance network performance. However, existing methods have limitations in capturing spatio-temporal features of 5G mobile traffic, particularly in areas with insufficient 5G coverage and limited historical 5G traffic data. To fill this gap, we introduce a regional feature conditioned diffusion framework for 5G network traffic generation. Our models explore the relationship between 5G traffic and existing 4G traffic, utilizing a customized cross attention mechanism and graph convolutional networks (GCN) to capture the correlation between network traffic and regional features. Based on this relationship, the framework can characterize mobile network traffic demands, thereby achieving high-fidelity 5G traffic generation in target regions with insufficient 5G coverage. Extensive experiments on real-world datasets have shown that the proposed scheme outperforms state-of-the-art baselines by more than 10%, demonstrating its high-fidelity generation capability, controllability, and generalizability. Moreover, we have deployed our scheme on China Mobile's Jiutian Platform as a network traffic simulator to improve 5G base station deployment strategies. | E28: 5G network traffic generation, Cross attention, Diffusion models, GCN | F28: 900 - No match | G28: 900 - No match | H28: [] | I28: [] | J28: =+LEN(H28) -> 2 | K28: =+LEN(I28) -> 2
... A30: /doi/10.1145/3659154.3659192 | B30: ACM | C30: An MEC-based Platform for IoT Applications | D30: The key technologies for the future development of mobile communications are: Provide end-to-end ultra-low latency, reliability and availability; Provide different network slices according to different business needs; Provide edge computing power; Smart network manage. Ultra-low latency and reliability and the ability to handle large-scale Internet of Things (IoT) connections are two important requirements. However, this cannot be achieved by simply improving the performance of wireless transmission (e.g. the radio access network). It is also necessary to improve the core network and creates edge computing platforms to achieve this goal. To address this issue, this article develops and deploys a mobile edge computing platform, also known as a multi-access edge computing (MEC) platform, to meet the requirements of ultra-low latency, high reliability, and massive connections. This article takes a smart pig farm as an example to demonstrate the design and deployment of an MEC applications. Specifically, this article develops an IoT system for the pig farm on the MEC platform and creates a virtualized MEC application to provide real-time packet processing and image recognition for the pig farm monitoring. In addition, this paper analyzes the performance of this MEC App, including the recognition accuracy and the latency in error recovery of the MEC App. | E30: Artificial Intelligence, CCS CONCEPTS:Wireless Networks, Networks | F30: 900 - No match | G30: 900 - No match | H30: [] | I30: [] | J30: =+LEN(H30) -> 2 | K30: =+LEN(I30) -> 2
A31: /doi/10.14778/3611540.3611617 | B31: ACM | C31: FS-Real: A Real-World Cross-Device Federated Learning Platform | D31: Federated learning (FL) is a general distributed machine learning paradigm that provides solutions for tasks where data cannot be shared directly. Due to the difficulties in communication management and heterogeneity of distributed data and devices, initiating and using an FL algorithm for real-world cross-device scenarios requires significant repetitive effort but may not be transferable to similar projects. To reduce the effort required for developing and deploying FL algorithms, we present FS-Real, an open-source FL platform designed to address the need of a general and efficient infrastructure for real-world cross-device FL. In this paper, we introduce the key components of FS-Real and demonstrate that FS-Real has the following capabilities: 1) reducing the programming burden of FL algorithm development with plug-and-play and adaptable runtimes on Android and other Internet of Things (IoT) devices; 2) handling a large number of heterogeneous devices efficiently and robustly with our communication management components; 3) supporting a wide range of advanced FL algorithms with flexible configuration and extension; 4) alleviating the costs and efforts for deployment, evaluation, simulation, and performance optimization of FL algorithms with automatized tool kits. | F31: 900 - No match | G31: 900 - No match | H31: [] | I31: [] | J31: =+LEN(H31) -> 2 | K31: =+LEN(I31) -> 2
A32: /doi/10.1145/3637528.3671528 | B32: ACM | C32: Know in AdVance: Linear-Complexity Forecasting of Ad Campaign Performance with Evolving User Interest | D32: Real-time Bidding (RTB) advertisers wish to | E32: campaign performance forecasting, real-time bidding, sequence modeling, user interest modeling | F32: 900 - No match | G32: 900 - No match | H32: [] | I32: [] | J32: =+LEN(H32) -> 2 | K32: =+LEN(I32) -> 2
A33: /doi/10.1145/3711912 | B33: ACM | C33: Unsupervised Framing Analysis for Social Media Discourse in Polarizing Events | D33: This study investigates the concept of | E33: Framing Analysis, Polarization, Social Network Analysis | F33: 900 - No match | G33: 900 - No match | H33: [] | I33: [] | J33: =+LEN(H33) -> 2 | K33: =+LEN(I33) -> 2
A34: /doi/10.1145/3637528.3671509 | B34: ACM | C34: FusionSF: Fuse Heterogeneous Modalities in a Vector Quantized Framework for Robust Solar Power Forecasting | D34: Accurate solar power forecasting is crucial to integrate photovoltaic plants into the electric grid, schedule and secure the power grid safety. This problem becomes more demanding for those newly installed solar plants which lack sufficient operational data. Current research predominantly relies on historical solar power data or numerical weather prediction in a single-modality format, ignoring the complementary information provided in different modalities. In this paper, we propose a multi-modality fusion framework to integrate historical power data, numerical weather prediction, and satellite images, significantly improving forecast performance. We introduce a vector quantized framework that aligns modalities with varying information densities, striking a balance between integrating sufficient information and averting model overfitting. Our framework demonstrates strong zero-shot forecasting capability, which is especially useful for those newly installed plants. Moreover, we collect and release a multi-modal solar power (MMSP) dataset from real-world plants to further promote the research of multi-modal solar forecasting algorithms. Our extensive experiments show that our model not only operates with robustness but also boosts accuracy in both zero-shot forecasting and scenarios rich with training data, surpassing leading models. We have incorporated it into our eForecaster platform and deployed it for more than 300 solar plants with a total capacity of over 15GW. Our code and dataset are accessible at https://github.com/DAMO-DI-ML/FusionSF.git. | E34: modality fusion, solar power forecasting, vector quantization, zero-shot learning | F34: 900 - No match | G34: 900 - No match | H34: [] | I34: [] | J34: =+LEN(H34) -> 2 | K34: =+LEN(I34) -> 2
A35: /doi/10.5555/3581644.3581711 | B35: ACM | C35: Performability Assessment of Containerized Multi-Tenant IMS through Multidimensional UGF | D35: We advance a performability assessment of a multi-tenant containerized IP Multimedia Subsystem (cIMS), i.e.: one and the same infrastructure is shared among different providers (or tenants). Specifically, we: | E35: IP multimedia subsystem, performability, redundancy optimization, universal generating function | F35: 900 - No match | G35: 900 - No match | H35: [] | I35: [] | J35: =+LEN(H35) -> 2 | K35: =+LEN(I35) -> 2
A36: /doi/10.1145/3555041.3589672 | B36: ACM | C36: Growing and Serving Large Open-domain Knowledge Graphs | D36: Applications of large open-domain knowledge graphs (KGs) to real-world problems pose many unique challenges. In this paper, we present extensions to Saga our platform for continuous construction and serving of knowledge at scale. In particular, we describe a pipeline for training knowledge graph embeddings that powers key capabilities such as fact ranking, fact verification, a related entities service, and support for entity linking. We then describe how our platform, including graph embeddings, can be leveraged to create a Semantic Annotation service that links unstructured Web documents to entities in our KG. Semantic annotation of the Web effectively expands our knowledge graph with edges to open-domain Web content which can be used in various search and ranking problems. Finally, we leverage annotated Web documents to drive Open-domain Knowledge Extraction. This targeted extraction framework identifies important coverage issues in the KG, then finds relevant data sources for target entities on the Web and extracts missing information to enrich the KG. Finally, we describe adaptations to our knowledge platform needed to construct and serve private personal knowledge on-device. This includes private incremental KG construction, cross- device knowledge sync, and global knowledge enrichment. | E36: information extraction, knowledge graphs, semantic annotation | F36: 900 - No match | G36: 900 - No match | H36: [] | I36: [] | J36: =+LEN(H36) -> 2 | K36: =+LEN(I36) -> 2
A37: /doi/10.1145/3589334.3645468 | B37: ACM | C37: MSynFD: Multi-hop Syntax Aware Fake News Detection | D37: The proliferation of social media platforms has fueled the rapid dissemination of fake news, posing threats to our real-life society. Existing methods use multimodal data or contextual information to enhance the detection of fake news by analyzing news content and/or its social context. However, these methods often overlook essential textual news content (articles) and heavily rely on sequential modeling and global attention to extract semantic information. These existing methods fail to handle the complex, subtle twists | E37: debiasing, fake news detection, graph neural network | F37: 900 - No match | G37: 900 - No match | H37: [] | I37: [] | J37: =+LEN(H37) -> 2 | K37: =+LEN(I37) -> 2
A38: /doi/10.1145/3495243.3560522 | B38: ACM | C38: A-mash: providing single-app illusion for multi-app use through user-centric UI mashup | D38: Mobile apps offer a variety of features that greatly enhance user experience. However, users still often find it difficult to use mobile apps in the way they want. For example, it is not easy to use multiple apps simultaneously on a small screen of a smartphone. In this paper, we present A-Mash, a mobile platform that aims to simplify the way of interacting with multiple apps concurrently to the level of using a single app only. A key feature of A-Mash is that users can | E38: mobile platform, multi app execution, multi-app single-screen, multi-tasking, user interface mashup | F38: 900 - No match | G38: 900 - No match | H38: [] | I38: [] | J38: =+LEN(H38) -> 2 | K38: =+LEN(I38) -> 2
A39: /doi/10.1145/3423459.3430760 | B39: ACM | C39: COVID-19 Joint Pandemic Modeling and Analysis Platform | D39: The non-pharmaceutical intervention to reduce the impact and spread of COVID-19 requires the development of policies and guidance through a collaborative effort among government, academia, medicine, and citizens. To operationalize this effort, we have developed an all-encompassing situational awareness platform that can process multi-modal and multi-source data allowing informed decision making. Besides, showing the current spread of infection, the platform also captures the impact of human dynamics on the infection spread, location, and availability of critical infrastructure, prediction, and high-performance computing driven simulation. The platform is extensible, allowing third-party integration and services to consume the curated data and analytics in near real-time. We believe the platform will augment critical decision making for reducing the impact and spread of the pandemic. | E39: distributed systems, real-time architectures, visualization | F39: 900 - No match | G39: 2 - Complete terms | H39: [] | I39: ['collaborative'] | J39: =+LEN(H39) -> 2 | K39: =+LEN(I39) -> 17
A40: /doi/10.1145/3510427.3510432 | B40: ACM | C40: Simulations of MRI Guided and Powered Ferric Applicators for Tetherless Delivery of Therapeutic Interventions | D40: Magnetic Resonance Imaging (MRI) is a well-established modality for pre-operative planning and is also explored for intra-operative guidance of procedures such as intravascular interventions. Among the experimental robot-assisted technologies, the magnetic field gradients of the MRI scanner are used to power and maneuver ferromagnetic applicators for accessing sites in the patientâ€™s body via the vascular network. In this work, we propose a computational platform for preoperative planning and modeling of MRI-powered applicators inside blood vessels. This platform was implemented as a two-way data and command pipeline that links the MRI scanner, the computational core, and the operator. The platform first processes multi-slice MR data to extract the vascular bed and then fits a virtual corridor inside the vessel. This corridor serves as a virtual fixture (VF), a forbidden region for the applicators to avoid vessel perforation or collision. The geometric features of the vessel centerline, the VF, and MRI safety compliance (dB/dt, max available gradient) are then used to generate magnetic field gradient waveforms. Different blood flow profiles can be user-selected, and those parameters are used for modeling the applicatorâ€™s maneuvering. The modeling module further generates cues about whether the selected vascular path can be safely maneuvered. Given future experimental studies that require a real-time operation, the platform was implemented on the Qt framework (C/C++) with software modules performing specific tasks running on dedicated threads: PID controller, generation of VF, generation of MR gradient waveforms. | E40: MRI, PID, VF, blood flow, blood vessels | F40: 2 - Complete acrs | G40: 900 - No match | H40: ['virtual environment', 'MRI', 'MR'] | I40: [] | J40: =+LEN(H40) -> 36 | K40: =+LEN(I40) -> 2
A41: /doi/10.1145/3626772.3657786 | B41: ACM | C41: DeCoCDR: Deployable Cloud-Device Collaboration for Cross-Domain Recommendation | D41: Cross-domain recommendation (CDR) is a widely used methodology in recommender systems to combat data sparsity. It leverages user data across different domains or platforms for providing personalized recommendations. Traditional CDR assumes user preferences and behavior data can be shared freely among cloud and users, which is now impractical due to strict restrictions of data privacy. In this paper, we propose a Deployment-friendly Cloud-Device Collaboration framework for Cross-Domain Recommendation (DeCoCDR). It splits CDR into a two-stage recommendation model through cloud-device collaborations, i.e., item-recall on cloud and item re-ranking on device. This design enables effective CDR while preserving data privacy for both the cloud and the device. Extensive offline and online experiments are conducted to validate the effectiveness of DeCoCDR. In offline experiments, DeCoCDR outperformed the state-of-the-arts in three large datasets. While in real-world deployment, DeCoCDR improved the conversion rate by 45.3% compared with the baseline. | E41: cloud-device collaboration, cross-domain recommendation, on-device inference, privacy presevation | F41: 900 - No match | G41: 2 - Complete terms | H41: [] | I41: ['collaboration'] | J41: =+LEN(H41) -> 2 | K41: =+LEN(I41) -> 17
A42: /doi/10.1145/3634814.3634836 | B42: ACM | C42: ContraPonzi: Smart Ponzi Scheme Detection for Ethereum via Contrastive Learning | D42: In recent years, blockchain technology has witnessed rapid development and received considerable attention. However, its decentralized and pseudonymous nature has also attracted many criminal activities. Among them, Ponzi schemes, a classic form of financial fraud, also hide their true face in smart contracts, causing huge losses to blockchain users. Although numerous methods have been proposed to detect Ponzi contracts, these methods still have limitations in terms of generalization and feature learning. To address this issue, we conduct research on Ethereum, the currently largest blockchain platform enabling smart contracts, and propose a novel contrastive learning-based smart Ponzi scheme detection method named ContraPonzi. This method first extracts control flow graph information from bytecodes and models it as attribute graphs that preserve both semantic and structural information. Next, by augmenting the bytecode data of multi-version compilers and maximizing the graph representation similarity of multi-version bytecodes of the same contract, a pre-training graph encoder is obtained and then can be used in Ponzi contract detection. Experimental results on real-world data demonstrate that ContraPonzi is significantly superior to the state-of-the-art in Ethereum Ponzi scheme detection. | E42: Contrastive Learning, Ethereum, Ponzi Schemes, Smart contract | F42: 900 - No match | G42: 900 - No match | H42: [] | I42: [] | J42: =+LEN(H42) -> 2 | K42: =+LEN(I42) -> 2
A43: /doi/10.1145/3560905.3568520 | B43: ACM | C43: BlastNet: Exploiting Duo-Blocks for Cross-Processor Real-Time DNN Inference | D43: In recent years, Deep Neural Network (DNN) has been increasingly adopted by a wide range of time-critical applications running on edge platforms with heterogeneous multiprocessors. To meet the stringent timing requirements of these applications, heterogeneous CPU and GPU resources must be efficiently utilized for the inference of multiple DNN models. Such a cross-processor real-time DNN inference paradigm poses major challenges due to the inherent performance imbalance among different processors and the lack of real-time support for cross-processor inference from existing deep learning frameworks. In this work, we propose a new system named BlastNet that exploits | E43: CPU-GPU heterogeneous platform, edge artificial intelligence, multi-DNN concurrent execution, neural architecture search, on-device deep learning, real-time scheduling | F43: 900 - No match | G43: 900 - No match | H43: [] | I43: [] | J43: =+LEN(H43) -> 2 | K43: =+LEN(I43) -> 2
A44: /doi/10.1145/3508352.3549437 | B44: ACM | C44: DARL: Distributed Reconfigurable Accelerator for Hyperdimensional Reinforcement Learning | D44: Reinforcement Learning (RL) is a powerful technology to solve decisionmaking problems such as robotics control. Modern RL algorithms, i.e., Deep Q-Learning, are based on costly and resource hungry deep neural networks. This motivates us to deploy alternative models for powering RL agents on edge devices. Recently, brain-inspired Hyper-Dimensional Computing (HDC) has been introduced as a promising solution for lightweight and efficient machine learning, particularly for classification. | F44: 3 - Modified acrs | G44: 900 - No match | H44: ['DARL'] | I44: [] | J44: =+LEN(H44) -> 8 | K44: =+LEN(I44) -> 2
A45: /doi/10.1145/3627673.3679128 | B45: ACM | C45: Advancing Multivariate Time Series Anomaly Detection: A Comprehensive Benchmark with Real-World Data from Alibaba Cloud | D45: Time series anomaly detection is of significant importance in many real-world applications, including finance, healthcare, network security, industrial equipment, complex computing systems, and space probes. Most of these applications involve multi-sensor systems, thus how to perform multivariate time series anomaly detection (MTSAD) has garnered widespread attention. This broad attention has fueled extensive research endeavors aimed to innovate and develop methods and techniques to improve the efficiency and precision of anomaly detection on multivariate time series data, including both classic machine learning methods and deep learning methods. However, evaluating the performance of these methods remains challenging due to the limited availability of public benchmark datasets for MTSAD, which are often criticized for various reasons. Additionally, there is no consensus on the best metrics for time series anomaly detection, further complicating MTSAD research. In this paper, we advance the benchmarking of time series anomaly detection by addressing datasets, evaluation metrics, and algorithm comparison. To the best of our knowledge, we have generated the largest real-world datasets for MTSAD using the Hologres AIOps system in the Alibaba Cloud platform. We review and compare popular evaluation metrics including recently proposed ones. To evaluate classic machine learning and recent deep learning methods fairly, we have conducted extensive comparisons of these methods on various datasets. We believe that our benchmarks and datasets will promote reproducible results and accelerate the progress of MTSAD research. | E45: anomaly detection, benchmark, datasets, time series | F45: 900 - No match | G45: 900 - No match | H45: [] | I45: [] | J45: =+LEN(H45) -> 2 | K45: =+LEN(I45) -> 2
A46: /doi/10.1145/3640468 | B46: ACM | C46: Multi-Task Learning with Sequential Dependence Toward Industrial Applications: A Systematic Formulation | D46: Multi-task learning (MTL) is widely used in the online recommendation and financial services for multi-step conversion estimation, but current works often overlook the sequential dependence among tasks. In particular, sequential dependence multi-task learning (SDMTL) faces challenges in dealing with complex task correlations and extracting valuable information in real-world scenarios, leading to negative transfer and a deterioration in the performance. Herein, a systematic learning paradigm of the SDMTL problem is established for the first time, which applies to more general multi-step conversion scenarios with longer conversion paths or various task dependence relationships. Meanwhile, an SDMTL architecture, named | E46: Multi-task learning, sequential dependency, negative transfer, industrial applications | F46: 900 - No match | G46: 900 - No match | H46: [] | I46: [] | J46: =+LEN(H46) -> 2 | K46: =+LEN(I46) -> 2
A47: /doi/10.1145/3583740.3626612 | B47: ACM | C47: AdaMap: High-Scalable Real-Time Cooperative Perception at the Edge | D47: Cooperative perception is the key approach to augment the perception of connected and automated vehicles (CAVs) toward safe autonomous driving. However, it is challenging to achieve real-time perception sharing for hundreds of CAVs in large-scale deployment scenarios. In this paper, we propose AdaMap, a new high-scalable real-time cooperative perception system, which achieves assured percentile end-to-end latency under time-varying network dynamics. To achieve AdaMap, we design a tightly coupled data plane and control plane. In the data plane, we design a new hybrid localization module to dynamically switch between object detection and tracking, and a novel point cloud representation module to adaptively compress and reconstruct the point cloud of detected objects. In the control plane, we design a new graph-based object selection method to un-select excessive multi-viewed point clouds of objects, and a novel approximated gradient descent algorithm to optimize the representation of point clouds. We implement AdaMap on an emulation platform, including realistic vehicle and server computation and a simulated 5G network, under a 150-CAV trace collected from the CARLA simulator. The evaluation results show that, AdaMap reduces up to 49x average transmission data size at the cost of 0.37 reconstruction loss, as compared to state-of-the-art solutions, which verifies its high scalability, adaptability, and computation efficiency. | E47: cooperative perception, point cloud compression, automotive edge computing | F47: 3 - Modified acrs | G47: 900 - No match | H47: ['CARLA'] | I47: [] | J47: =+LEN(H47) -> 9 | K47: =+LEN(I47) -> 2
A48: /doi/10.1145/3609389.3610565 | B48: ACM | C48: SymbIoT: Towards An Extensible Blockchain Integration Testbed for IIoT | D48: This paper presents SymbIoT, an extensible hybrid simulation-emulation testbed to investigate the integration of blockchain and distributed ledger technology (DLT) within the Industrial Internet of Things (IIoT) continuum. By adopting a joint software and hardware-based approach, we amalgamate the flexibility of software solutions and the real-world applicability offered by integrating comparable IoT hardware. The versatility of SymbIoT lies in its extensibility, offering flexibility in parameters including consensus algorithms, block size, node count and topology, throughput limitation, and use-case application deployment. SymbIoT facilitates comprehensive empirical studies of blockchain implementations within IIoT, focusing on performance, scalability, and security considerations. The testbed provides a platform for innovative and pragmatic experimentation in blockchain and IIoT integration, holding promise for shaping future applications and solutions in this cross-disciplinary field. We also present results from preliminary experimentation, indicating the applicability of the testbed for IIoT and broader IoT-to-cloud scenarios. | E48: blockchain, IoT, testbed, IIoT | F48: 900 - No match | G48: 900 - No match | H48: [] | I48: [] | J48: =+LEN(H48) -> 2 | K48: =+LEN(I48) -> 2
A49: /doi/10.1109/TNET.2022.3196806 | B49: ACM | C49: Nationwide Deployment and Operation of a Virtual Arrival Detection System in the Wild | D49: We report a 30-month nationwide deployment and operation study of an indoor arrival detection system based on Bluetooth Low Energy called VALID in 364 Chinese cities. VALID is pilot-studied, deployed, and operated in the wild to infer real-time indoor arrival status of couriers, and improve their status reporting behavior based on the detection. During its full nationwide operation (2018/12-2021/01), VALID consists of virtual devices at 3 million shops and restaurants, where 530,859 of them are in multi-story malls and markets to infer and influence 1 million couriersâ€™ behavior, and assist the scheduling of 3.9 billion orders for 186 million customers. Although indoor arrival detection is straightforward in controlled environments, the scale of our platform makes the cost prohibitively high. In this work, we explore to use merchantsâ€™ smartphones under their consent as a virtual infrastructure to design, build, deploy, and operate VALID from in-lab conception to nationwide operation in three phases for 30 months. We consider metrics including system evolution, reliability, utility, participation, energy, privacy, monetary benefits, along with couriersâ€™ behavior changes. We share three lessons and their implications for similar wireless sensing or communication systems with large geospatial operations. | F49: 900 - No match | G49: 900 - No match | H49: [] | I49: [] | J49: =+LEN(H49) -> 2 | K49: =+LEN(I49) -> 2
A50: /doi/10.1145/3394885.3431516 | B50: ACM | C50: Energy-Performance Co-Management of Mixed-Sensitivity Workloads on Heterogeneous Multi-core Systems | D50: Satisfying performance of complex workload scenarios with respect to energy consumption on Heterogeneous Multi-core Platforms (HMPs) is challenging when considering i) the increasing variety of applications, and ii) the large space of resource management configurations. Existing run-time resource management approaches use online and offline learning to handle such complexity. However, they focus on one type of application, neglecting concurrent execution of mixed sensitivity workloads. In this work, we propose an energy-performance co-management method which prioritizes mixed type of applications at run-time, and searches in the configuration space to find the optimal configuration for each application which satisfies the performance requirements while saving energy. We evaluate our approach on a real Odroid XU3 platform over mixed-sensitivity embedded workloads. Experimental results show our approach provides 54% lower performance violation with 50% higher energy saving compared to the existing approaches. | E50: Concurrent applications, Heterogeneous Multi-core Systems, On-chip Resource allocation, Performance, latency, throughput | F50: 900 - No match | G50: 900 - No match | H50: [] | I50: [] | J50: =+LEN(H50) -> 2 | K50: =+LEN(I50) -> 2
A51: /doi/10.1145/3581783.3612425 | B51: ACM | C51: TikTalk: A Video-Based Dialogue Dataset for Multi-Modal Chitchat in Real World | D51: To facilitate the research on intelligent and human-like chatbots with multi-modal context, we introduce a new video-based multi-modal dialogue dataset, called TikTalk. We collect 38K videos from a popular video-sharing platform, along with 367K conversations posted by users beneath them. Users engage in spontaneous conversations based on their multi-modal experiences from watching videos, which helps recreate real-world chitchat context. Compared to previous multi-modal dialogue datasets, the richer context types in TikTalk lead to more diverse conversations, but also increase the difficulty in capturing human interests from intricate multi-modal information to generate personalized responses. Moreover, external knowledge is more frequently evoked in our dataset. These facts reveal new challenges for multi-modal dialogue models. We quantitatively demonstrate the characteristics of TikTalk, propose a video-based multi-modal chitchat task, and evaluate several dialogue baselines. Experimental results indicate that the models incorporating large language models (LLM) can generate more diverse responses, while the model utilizing knowledge graphs to introduce external knowledge performs the best overall. Furthermore, no existing model can solve all the above challenges well. There is still a large room for future improvements, even for LLM with visual extensions. Our dataset is available at https://ruc-aimind.github.io/projects/TikTalk/. | E51: chitchat, dataset, multi-modal dialogue, real world | F51: 900 - No match | G51: 900 - No match | H51: [] | I51: [] | J51: =+LEN(H51) -> 2 | K51: =+LEN(I51) -> 2
A52: /doi/10.1145/3640457.3688147 | B52: ACM | C52: End-to-End Cost-Effective Incentive Recommendation under Budget Constraint with Uplift Modeling | D52: In modern online platforms, incentives (e.g., discounts, bonus) are essential factors that enhance user engagement and increase platform revenue. Over recent years, uplift modeling has been introduced as a strategic approach to assign incentives to individual customers. Especially in many real-world applications, online platforms can only incentivize customers with specific budget constraints. This problem can be reformulated as the multi-choice knapsack problem (MCKP). The objective of this optimization is to select the optimal incentive for each customer to maximize the return on investment (ROI). Recent works in this field frequently tackle the budget allocation problem using a two-stage approach. However, this solution is confronted with the following challenges: (1) The causal inference methods often ignore the domain knowledge in online marketing, where the expected response curve of a customer should be monotonic and smooth as the incentive increases. (2) There is an optimality gap between the two stages, resulting in inferior sub-optimal allocation performance due to the loss of the incentive recommendation information for the uplift prediction under the limited budget constraint. To address these challenges, we propose a novel End-to-End Cost-Effective Incentive Recommendation (E3IR) model under the budget constraint. Specifically, our methods consist of two modules, i.e., the uplift prediction module and the differentiable allocation module. In the uplift prediction module, we construct prediction heads to capture the incremental improvement between adjacent treatments with the marketing domain constraints (i.e., monotonic and smooth). We incorporate integer linear programming (ILP) as a differentiable layer input in the differentiable allocation module. Furthermore, we conduct extensive experiments on public and real product datasets, demonstrating that our E3IR improves allocation performance compared to existing two-stage approaches. | E52: Budget Constraint, End-to-End Optimization, Incentive Recommendation, Uplift Modeling | F52: 900 - No match | G52: 900 - No match | H52: [] | I52: [] | J52: =+LEN(H52) -> 2 | K52: =+LEN(I52) -> 2
A53: /doi/10.14778/3561261.3561266 | B53: ACM | C53: Privacy-preserving cooperative online matching over spatial crowdsourcing platforms | D53: With the continuous development of spatial crowdsourcing platform, online task assignment problem has been widely studied as a typical problem in spatial crowdsourcing. Most of the existing studies are based on a single-platform task assignment to maximize the platform's revenue. Recently, cross online task assignment has been proposed, aiming at increasing the mutual benefit through cooperations. However, existing methods fail to consider the data privacy protection in the process of cooperation and cause the leakage of sensitive data such as the location of a request and the historical data of cooperative platforms. In this paper, we propose Privacy-preserving Cooperative Online Matching (PCOM), which protects the privacy of the users and workers on their respective platforms. We design a PCOM framework and provide theoretical proof that the framework satisfies the differential privacy property. We then propose two PCOM algorithms based on two different privacy-preserving strategies. Extensive experiments on real and synthetic datasets confirm the effectiveness and efficiency of our algorithms. | F53: 900 - No match | G53: 900 - No match | H53: [] | I53: [] | J53: =+LEN(H53) -> 2 | K53: =+LEN(I53) -> 2
A54: /doi/10.1145/3597926.3598070 | B54: ACM | C54: Building Critical Testing Scenarios for Autonomous Driving from Real Accidents | D54: One of the aims of the development and spread of autonomous driving technology is to reduce traffic accidents caused by human factors. But recently reported data on fatal accidents involving autonomous driving system (ADS) shows that this important goal has not been achieved. So there is an emerge requirement on more comprehensive and targeted testing especially on safe driving. In this paper, we propose an approach to automatically building critical testing scenarios from real-world accident data. Firstly, we propose a new model called M-CPS (Multi-channel Panoptic Segmentation) to extract the effective information from the accident record (such as images or videos), and separate the independent individuals of different traffic participants for further scene recovery. Compared with the traditional panoramic segmentation models, M-CPS model is able to effectively handle segmentation challenges due to the shooting angle, image quality, pixel overlap and other problems existing in the accident record. Next, the extracted core information is then connected with the virtual testing platform to generate the original scene set. Besides, we also design a mutation testing solution on the basis of the original scene set, thus greatly enriching the scene library for testing. In our experiments, the M-CPS model reaches a result of 66.1% PQ on CityScapes test set, shows that our model has only slight fluctuations on performance compared with the best benchmark model on pure panoptic segmentation task. It also reaches a result of 84.5% IoU for semantic segmentation branch and 40.3% mAP for instance segmentation branch on SHIFT dataset. Then we use UCF-Crime, CADP and US-Accidents datasets to generate the original and mutated scene set. Those generated scene sets are connected to Apollo and Carla simulation platforms to test ADS prototypes. We find three types of scenarios that can lead to accidents of ADS prototypes, which indicates that the existing ADS prototype has defects. Our solution provides a new possible direction for the recovery of key scenarios in ADS testing, and can improve the efficiency in related fields. | E54: Autonomous Driving Systems, Panoptic Segmentation, Parameter Mutation, Scene Recovery, Testing | F54: 900 - No match | G54: 900 - No match | H54: [] | I54: [] | J54: =+LEN(H54) -> 2 | K54: =+LEN(I54) -> 2
A55: /doi/10.1145/3708537 | B55: ACM | C55: Relieving Overexposure in Information Diffusion Through a Budget Multi-stage Allocation | D55: When information dissemination campaigns on Online Social Networking platforms are too aggressive, this can easily cause information overexposure. Overexposure can break through the psychological and physiological limits that the audience can tolerate, making it difficult for the audience to obtain reasonable cognitive concepts. For example, the overexposure of information referring to an object in a promotional campaign can lead to inflated expectations in individuals. Building on this, we introduce two indicators for individualsâ€™ expectations and actual utility of the object and design a multi-stage triggered mechanism for seed individuals to explore the relieving overexposure problem in information diffusion. We build a multi-stage information diffusion model and characterize the evolution of individual expectations. We verify the hardness result of the relieving overexposure problem by budget multi-stage allocation, and the non-submodularity and non-monotonicity of the objective function. Addressing the non-monotonic and non-submodular set function, we provide a direct influence-oriented algorithm with a greedy approach. Extensive experiments are performed on four real networks to explore how model parameters and network properties affect the effects of multi-stage triggered strategies for seed individuals. Using the experiments, we found that the seed individual multi-stage incremental triggered strategy of dissemination campaign of information referring to an object shows better performance, and the lower the actual utility of the specific object, the more accurate the promotion strategy needs to be developed. | E55: Relieving overexposure, Social network, Influence maximization, Budget multi-stage allocation | F55: 900 - No match | G55: 900 - No match | H55: [] | I55: [] | J55: =+LEN(H55) -> 2 | K55: =+LEN(I55) -> 2
A56: /doi/10.1145/3640457.3688098 | B56: ACM | C56: A Multi-modal Modeling Framework for Cold-start Short-video Recommendation | D56: Short video has witnessed rapid growth in the past few years in multimedia platforms. To ensure the freshness of the videos, platforms receive a large number of user-uploaded videos every day, making collaborative filtering-based recommender methods suffer from the item cold-start problem (e.g., the new-coming videos are difficult to compete with existing videos). Consequently, increasing efforts tackle the cold-start issue from the content perspective, focusing on modeling the multi-modal preferences of users, a fair way to compete with new-coming and existing videos. However, recent studies ignore the existing gap between multi-modal embedding extraction and user interest modeling as well as the discrepant intensities of user preferences for different modalities. In this paper, we propose M3CSR, a multi-modal modeling framework for cold-start short video recommendation. Specifically, we preprocess content-oriented multi-modal features for items and obtain trainable category IDs by performing clustering. In each modality, we combine modality-specific cluster ID embedding and the mapped original modality feature as modality-specific representation of the item to address the gap. Meanwhile, M3CSR measures the user modality-specific intensity based on the correlation between modality-specific interest and behavioral interest and employs pairwise loss to further decouple user multi-modal interests. Extensive experiments on four real-world datasets demonstrate the superiority of our proposed model. The framework has been deployed on a billion-user scale short video application and has shown improvements in various commercial metrics within cold-start scenarios. | E56: Cold-start, Multi-modal Modeling, Recommender System | F56: 900 - No match | G56: 2 - Complete terms | H56: [] | I56: ['collaborative'] | J56: =+LEN(H56) -> 2 | K56: =+LEN(I56) -> 17
A57: /doi/10.1145/3229089 | B57: ACM | C57: XD-AR: Challenges and Opportunities in Cross-Device Augmented Reality Application Development | D57: Augmented Reality (AR) developers face a proliferation of new platforms, devices, and frameworks. This often leads to applications being limited to a single platform and makes it hard to support collaborative AR scenarios involving multiple different devices. This paper presents XD-AR, a cross-device AR application development framework designed to unify input and output across hand-held, head-worn, and projective AR displays. XD-AR's design was informed by challenging scenarios for AR applications, a technical review of existing AR platforms, and a survey of 30 AR designers, developers, and users. Based on the results, we developed a taxonomy of AR system components and identified key challenges and opportunities in making them work together. We discuss how our taxonomy can guide the design of future AR platforms and applications and how cross-device interaction challenges could be addressed. We illustrate this when using XD-AR to implement two challenging AR applications from the literature in a device-agnostic way. | E57: augmented reality, cross-device development, framework, taxonomy | F57: 1 - Complete terms | G57: 2 - Complete terms | H57: ['augmented reality', 'virtual environment', 'AR'] | I57: ['collaborative'] | J57: =+LEN(H57) -> 50 | K57: =+LEN(I57) -> 17
A58: /doi/10.1145/3492323.3503507 | B58: ACM | C58: An urban sensing architecture as essential infrastructure for future cities | D58: Climate change and migration have become one of the most challenging problems for our civilization. In this context, city councils work hard to manage essential services for citizens such as waste collection, street lamp lighting, and water supply. Increasingly, digitalization and the Internet of Things (IoT) help cities improve services, increase productivity and reduce costs. However, to understand how this may happen, we explore the urban sensing capabilities from citizen- to city-scale, how sensing at different levels is interlinked, and the challenges of managing innovations based on IoT data and devices. | E58: IoT, data monitoring infrastructure, urban sensing | F58: 900 - No match | G58: 900 - No match | H58: [] | I58: [] | J58: =+LEN(H58) -> 2 | K58: =+LEN(I58) -> 2
A59: /doi/10.1145/3459637.3482353 | B59: ACM | C59: iMap: Incremental Node Mapping between Large Graphs Using GNN | D59: Node mapping between large graphs (or network alignment) plays a key preprocessing role in joint-graph data mining applications like social link prediction, cross-platform recommendation, etc. Most existing approaches attempt to perform alignment at the granularity of entire graphs, while handling the whole graphs may lower the scalability and the noisy nodes/edges in the graphs may impact the effectiveness. From the observation that potential node mappings always appear near known corresponding nodes, we propose iMAP, a novel sub-graph expansion based alignment framework to incrementally construct meaningful sub-graphs and perform alignment on each sub-graph pair iteratively, which reduces the unnecessary computation cost in the original raw networks and improves effectiveness via excluding possible noises. Specifically, iMap builds a candidate sub-graph around known matched nodes initially. In each following iteration, iMap trains an alignment model to infer the node mapping relationship between sub-graphs, from which the sub-graphs are further extended and refined. In addition, we design a Graph Neural Network(GNN) based model named MAP on each sub-graph pair in the iMap framework. MAP utilizes trainable Multi-layer Perception (MLP) prediction heads for similarity computation and employs a mixed loss function consisting of the ranking loss for contrastive learning and the cross-entropy loss for classification. Extensive experiments conducted on real social networks demonstrate superior efficiency and effectiveness (above 12% improvement) of our proposed method compared to several state-of-the-art methods. | E59: graph neural network, network alignment, sub-graph expansion | F59: 900 - No match | G59: 1 - Complete terms cross | H59: [] | I59: ['cross-platform'] | J59: =+LEN(H59) -> 2 | K59: =+LEN(I59) -> 18
A60: /doi/10.1145/3643677 | B60: ACM | C60: Analyzing and Detecting Information Types of Developer Live Chat Threads | D60: Online chatrooms serve as vital platforms for information exchange among software developers. With multiple developers engaged in rapid communication and diverse conversation topics, the resulting chat messages often manifest complexity and lack structure. To enhance the efficiency of extracting information from chat | E60: Developer chatroom, information type classification, data augmentation, deep learning | F60: 900 - No match | G60: 900 - No match | H60: [] | I60: [] | J60: =+LEN(H60) -> 2 | K60: =+LEN(I60) -> 2
A61: /doi/10.1145/3394171.3413759 | B61: ACM | C61: Price Suggestion for Online Second-hand Items with Texts and Images | D61: This paper presents an intelligent price suggestion system for online second-hand listings based on their uploaded images and text descriptions. The goal of price prediction is to help sellers set effective and reasonable prices for their second-hand items with the images and text descriptions uploaded to the online platforms. Specifically, we design a multi-modal price suggestion system which takes as input the extracted visual and textual features along with some statistical item features collected from the second-hand item shopping platform to determine whether the image and text of an uploaded second-hand item are qualified for reasonable price suggestion with a binary classification model, and provide price suggestions for second-hand items with qualified images and text descriptions with a regression model. To satisfy different demands, two different constraints are added into the joint training of the classification model and the regression model. Moreover, a customized loss function is designed for optimizing the regression model to provide price suggestions for second-hand items, which can not only maximize the gain of the sellers but also facilitate the online transaction. We also derive a set of metrics to better evaluate the proposed price suggestion system. Extensive experiments on a large real-world dataset demonstrate the effectiveness of the proposed multi-modal price suggestion system. | E61: deep neural network, joint optimization, online second-hand item, price suggestion | F61: 900 - No match | G61: 900 - No match | H61: [] | I61: [] | J61: =+LEN(H61) -> 2 | K61: =+LEN(I61) -> 2
A62: /doi/10.1145/3459637.3481928 | B62: ACM | C62: Influence Maximization in Multi-Relational Social Networks | D62: Influence maximization (IM) is a classic problem, which aims to find a set of k users (called seed set) in a social network such that the expected number of users influenced by the seed users is maximized. Existing IM algorithms mainly focus on one-by-one influence diffusion among users with friendships. However, in addition to 1-to-1 friendships, 1-to-N group relations usually exist in real social platforms, which are seldom fully exploited by conventional methods. | E62: influence maximization, social influence, social network analysis | F62: 900 - No match | G62: 900 - No match | H62: [] | I62: [] | J62: =+LEN(H62) -> 2 | K62: =+LEN(I62) -> 2
A63: /doi/10.1145/3624062.3624107 | B63: ACM | C63: Localization of Gamma-ray Bursts in a Balloon-Borne Telescope | D63: Multi-messenger astrophysics combines observations from multiple instruments to study transient astrophysical phenomena, many occurring at seconds-level timescales. To identify and precisely localize these events in the sky, current systems often search through extensive sensor data, requiring resource-intensive computation to achieve results on the timescale of the events themselves. We seek to reduce computational requirements so as to perform real-time event localization with limited computational resources suitable for an orbital platform. | E63: gamma-ray astronomy, multi-messenger astrophysics | F63: 900 - No match | G63: 900 - No match | H63: [] | I63: [] | J63: =+LEN(H63) -> 2 | K63: =+LEN(I63) -> 2
A64: /doi/10.1145/3503823.3503863 | B64: ACM | C64: Three Gods in Eleusis: Discovering Tangible and Intangible Cultural Heritage of Ancient Eleusis | D64: The present study concerns the design and implementation of a serious game for the on-site and remote promotion and dissemination of knowledge regarding the mythology of ancient Eleusis in an interactive, fun and educational way. Specifically, while playing, the user discovers artifacts exhibited in the archaeological museum and related to the archaeological site of Eleusis, unfolding the content of the myth of Persephone. The story takes place in a realistic three-dimensional virtual environment that simulates the Archaeological Museum of Eleusis. The selected archaeological artifacts, in combination with the narration of the myth of Persephone, transfer the knowledge about the historicity of the place in an experientially playful way. The main purpose of the study is to introduce a novel, interactive playful narrative digital museum experience, in which the user is guided through a mechanism to simultaneously acquire knowledge both for the intangible and tangible heritage of a site with significant historical value. The evolution of the scenario (story) is dynamic and based on the choices of the user. The content (text etc.) of the system is presented through a dynamic multilingual approach, which offers the management of multiple different languages and personalized content based on the target group. The system relies on cross-platform technologies to cover a wide range of users. | E64: Eleusis, Game-Based Learning, Myth of Persephone, Serious Games, Tangible and Intangible Cultural Heritage | F64: 900 - No match | G64: 1 - Complete terms cross | H64: [] | I64: ['cross-platform', 'virtual environment'] | J64: =+LEN(H64) -> 2 | K64: =+LEN(I64) -> 41
A65: /doi/10.1145/3340531.3412713 | B65: ACM | C65: Improving Multi-Scenario Learning to Rank in E-commerce by Exploiting Task Relationships in the Label Space | D65: Traditional Learning to Rank (LTR) models in E-commerce are usually trained on logged data from a single domain. However, data may come from multiple domains, such as hundreds of countries in international E-commerce platforms. Learning a single ranking function obscures domain differences, while learning multiple functions for each domain may also be inferior due to ignoring the correlations between domains. It can be formulated as a multi-task learning problem where multiple tasks share the same feature and label space. To solve the above problem, which we name Multi-Scenario Learning to Rank, we propose the Hybrid of implicit and explicit Mixture-of-Experts (HMoE) approach. Our proposed solution takes advantage of Multi-task Mixture-of-Experts to implicitly identify distinctions and commonalities between tasks in the feature space, and improves the performance with a stacked model learning task relationships in the label space explicitly. Furthermore, to enhance the flexibility, we propose an end-to-end optimization method with a task-constrained back-propagation strategy. We empirically verify that the optimization method is more effective than two-stage optimization required by the stacked approach. Experiments on real-world industrial datasets demonstrate that HMoE significantly outperforms the popular multi-task learning methods. HMoE is in-use in the search system of AliExpress and achieved 1.92% revenue gain in the period of one-week online A/B testing. We also release a sampled version of our dataset to facilitate future research. | E65: e-commerce, learning to rank, multi-task learning, neural networks | F65: 900 - No match | G65: 900 - No match | H65: [] | I65: [] | J65: =+LEN(H65) -> 2 | K65: =+LEN(I65) -> 2
... A74: /doi/10.1145/3604915.3608792 | B74: ACM | C74: Online Matching: A Real-time Bandit System for Large-scale Recommendations | D74: The last decade has witnessed many successes of deep learning-based models for industry-scale recommender systems. These models are typically trained offline in a batch manner. While being effective in capturing usersâ€™ past interactions with recommendation platforms, batch learning suffers from long model-update latency and is vulnerable to system biases, making it hard to adapt to distribution shift and explore new items or user interests. Although online learning-based approaches (e.g., multi-armed bandits) have demonstrated promising theoretical results in tackling these challenges, their practical real-time implementation in large-scale recommender systems remains limited. First, the scalability of online approaches in servicing a massive online traffic while ensuring timely updates of bandit parameters poses a significant challenge. Additionally, exploring uncertainty in recommender systems can easily result in unfavorable user experience, highlighting the need for devising intricate strategies that effectively balance the trade-off between exploitation and exploration. In this paper, we introduce Online Matching: a scalable closed-loop bandit system learning from usersâ€™ direct feedback on items in real time. We present a hybrid offline + online approach for constructing this system, accompanied by a comprehensive exposition of the end-to-end system architecture. We propose Diag-LinUCB â€“ a novel extension of the LinUCB algorithm â€“ to enable distributed updates of bandits parameter in a scalable and timely manner. We conduct live experiments in YouTube and show that Online Matching is able to enhance the capabilities of fresh content discovery and item exploration in the present platform. | E74: bandits algorithms, information retrieval, neural networks, real-time recommenders, recommender systems | F74: 900 - No match | G74: 900 - No match | H74: [] | I74: [] | J74: =+LEN(H74) -> 2 | K74: =+LEN(I74) -> 2
A75: /doi/10.1145/3616901.3616944 | B75: ACM | C75: Realistic 3D Modeling Method of Virtual Traditional Chinese Medicine | D75: In order to realize the 3D construction and simulation of virtual traditional Chinese medicine with high realism. Taking the confusing Chinese medicine Radix Phytolaccae and Ginseng slices as an example, starting from morphological identification of traditional Chinese medicine, constructing the 3D model of its appearance, using physically based rendering(PBR) technology based on its geometry, color, texture, surface and cross section for 3D realistic simulation. By rendering in the Arnold built in Maya, and the 3D game engine software Unity3d, using PBR process technology to build visual traditional Chinese medicines can accurately present the surface texture characteristics of traditional Chinese medicine and achieve a more realistic rendering effect. The production method based on PBR mapping can be applied to different 3D software platforms, and can show realistic rendering effects, which is more realistic and efficient than traditional mapping methods. | F75: 900 - No match | G75: 900 - No match | H75: [] | I75: [] | J75: =+LEN(H75) -> 2 | K75: =+LEN(I75) -> 2
A76: /doi/10.1145/3383313.3412236 | B76: ACM | C76: Progressive Layered Extraction (PLE): A Novel Multi-Task Learning (MTL) Model for Personalized Recommendations | D76: Multi-task learning (MTL) has been successfully applied to many recommendation applications. However, MTL models often suffer from performance degeneration with negative transfer due to the complex and competing task correlation in real-world recommender systems. Moreover, through extensive experiments across SOTA MTL models, we have observed an interesting seesaw phenomenon that performance of one task is often improved by hurting the performance of some other tasks. To address these issues, we propose a Progressive Layered Extraction (PLE) model with a novel sharing structure design. PLE separates shared components and task-specific components explicitly and adopts a progressive routing mechanism to extract and separate deeper semantic knowledge gradually, improving efficiency of joint representation learning and information routing across tasks in a general setup. We apply PLE to both complicatedly correlated and normally correlated tasks, ranging from two-task cases to multi-task cases on a real-world Tencent video recommendation dataset with 1 billion samples, and results show that PLE outperforms state-of-the-art MTL models significantly under different task correlations and task-group size. Furthermore, online evaluation of PLE on a large-scale content recommendation platform at Tencent manifests 2.23% increase in view-count and 1.84% increase in watch time compared to SOTA MTL models, which is a significant improvement and demonstrates the effectiveness of PLE. Finally, extensive offline experiments on public benchmark datasets demonstrate that PLE can be applied to a variety of scenarios besides recommendations to eliminate the seesaw phenomenon. PLE now has been deployed to the online video recommender system in Tencent successfully. | E76: Multi-task Learning, Recommender System, Seesaw Phenomenon | F76: 900 - No match | G76: 900 - No match | H76: [] | I76: [] | J76: =+LEN(H76) -> 2 | K76: =+LEN(I76) -> 2
A77: /doi/10.1145/3609386 | B77: ACM | C77: MaGNAS: A Mapping-Aware Graph Neural Architecture Search Framework for Heterogeneous MPSoC Deployment | D77: Graph Neural Networks (GNNs) are becoming increasingly popular for vision-based applications due to their intrinsic capacity in modeling structural and contextual relations between various parts of an image frame. On another front, the rising popularity of deep vision-based applications at the edge has been facilitated by the recent advancements in heterogeneous multi-processor Systems on Chips (MPSoCs) that enable inference under real-time, stringent execution requirements. By extension, GNNs employed for vision-based applications must adhere to the same execution requirements. Yet contrary to typical deep neural networks, the irregular flow of graph learning operations poses a challenge to running GNNs on such heterogeneous MPSoC platforms. In this paper, we propose a novel unified | E77: Graph neural networks, MPSoCs, HW-SW codesign, edge computing | F77: 900 - No match | G77: 900 - No match | H77: [] | I77: [] | J77: =+LEN(H77) -> 2 | K77: =+LEN(I77) -> 2
A78: /doi/10.1145/3219819.3219928 | B78: ACM | C78: MIX: Multi-Channel Information Crossing for Text Matching | D78: Short Text Matching plays an important role in many natural language processing tasks such as information retrieval, question answering, and conversational system. Conventional text matching methods rely on predefined templates and rules, which are not applicable to short text with limited numebr of words and limit their ability to generalize to unobserved data. Many recent efforts have been made to apply deep neural network models to natural language processing tasks, which reduces the cost of feature engineering. In this paper, we present the design of Multi-Channel Information Crossing, a multi-channel convolutional neural network model for text matching, with additional attention mechanisms from sentence and text semantics. MIX compares text snippets at varied granularities to form a series of multi-channel similarity matrices, which are crossed with another set of carefully designed attention matrices to expose the rich structures of sentences to deep neural networks. We implemented MIX and deployed the system on Tencent's Venus distributed computation platform. Thanks to carefully engineered multi-channel information crossing, evaluation results suggest that MIX outperforms a wide range of state-of-the-art deep neural network models by at least 11.1% in terms of the normalized discounted cumulative gain (NDCG@3), on the English WikiQA dataset. Moreover, we also performed online A/B tests with real users on the search service of Tencent QQ Browser. Results suggest that MIX raised the number of clicks on the returned results by 5.7%, due to an increased accuracy in query-document matching, which demonstrates the superior performance of MIX in production environments. | E78: ad-hoc retrieval, attention mechanism, convolutional neural networks, question answering, text matching | F78: 900 - No match | G78: 900 - No match | H78: [] | I78: [] | J78: =+LEN(H78) -> 2 | K78: =+LEN(I78) -> 2
A79: /doi/10.1145/3394486.3403201 | B79: ACM | C79: Multi-level Graph Convolutional Networks for Cross-platform Anchor Link Prediction | D79: Cross-platform account matching plays a significant role in social network analytics, and is beneficial for a wide range of applications. However, existing methods either heavily rely on high-quality user generated content (including user profiles) or suffer from data insufficiency problem if only focusing on network topology, which brings researchers into an insoluble dilemma of model selection. In this paper, to address this problem, we propose a novel framework that considers multi-level graph convolutions on both local network structure and hypergraph structure in a unified manner. The proposed method overcomes data insufficiency problem of existing work and does not necessarily rely on user demographic information. Moreover, to adapt the proposed method to be capable of handling large-scale social networks, we propose a two-phase space reconciliation mechanism to align the embedding spaces in both network partitioning based parallel training and account matching across different social networks. Extensive experiments have been conducted on two large-scale real-life social networks. The experimental results demonstrate that the proposed method outperforms the state-of-the-art models with a big margin. | E79: account matching, anchor link prediction, network embedding | F79: 900 - No match | G79: 1 - Complete terms cross | H79: [] | I79: ['cross-platform'] | J79: =+LEN(H79) -> 2 | K79: =+LEN(I79) -> 18
A80: /doi/10.1145/2968478.2968480 | B80: ACM | C80: Real-time cache management for multi-core virtualization | D80: Real-time virtualization techniques have been investigated with the primary goal of consolidating multiple real-time systems onto a single hardware platform while ensuring timing predictability. However, a shared last-level cache (LLC) on recent multi-core platforms can easily hamper timing predictability due to the resulting temporal interference among consolidated workloads. Since such interference caused by the LLC is highly variable and may have not even existed in legacy systems to be consolidated, it poses a significant challenge for real-time virtualization. In this paper, we propose a real-time cache management framework for multi-core virtualization. Our framework introduces two hypervisor-level techniques, vLLC and vColoring, that enable the cache allocation of individual tasks running in a virtual machine (VM), which is not achievable by the current state of the art. Our framework also provides a cache management scheme that determines cache allocation to tasks, designs VMs in a cache-aware manner, and minimizes the aggregated utilization of VMs to be consolidated. As a proof of concept, we implemented vLLC and vColoring in the KVM hypervisor running on x86 and ARM multi-core platforms. Experimental results with three different guest OSs, namely Linux/RK, vanilla Linux and MS Windows Embedded, show that our techniques can effectively control the cache allocation of tasks in VMs. Our cache management scheme yields a significant utilization benefit compared to other approaches. | F80: 3 - Modified acrs | G80: 900 - No match | H80: ['ARM'] | I80: [] | J80: =+LEN(H80) -> 7 | K80: =+LEN(I80) -> 2
A81: /doi/10.1145/3689754 | B81: ACM | C81: Making Formulog Fast: An Argument for Unconventional Datalog Evaluation | D81: With its combination of Datalog, SMT solving, and functional programming, the language Formulog provides an appealing mix of features for implementing SMT-based static analyses (e.g., refinement type checking, symbolic execution) in a natural, declarative way. At the same time, the performance of its custom Datalog solver can be an impediment to using Formulog beyond prototypingâ€”a common problem for Datalog variants that aspire to solve large problem instances. In this work we speed up Formulog evaluation, with some surprising results: while 2.2Ã— speedups can be obtained by using the conventional techniques for high-performance Datalog (e.g., compilation, specialized data structures), the big wins come by abandoning the central assumption in modern performant Datalog engines, semi-naive Datalog evaluation. In the place of semi-naive evaluation, we develop eager evaluation, a concurrent Datalog evaluation algorithm that explores the logical inference space via a depth-first traversal order. In practice, eager evaluation leads to an advantageous distribution of Formulogâ€™s SMT workload to external SMT solvers and improved SMT solving times: our eager evaluation extensions to the Formulog interpreter and SoufflÃ©â€™s code generator achieve mean 5.2Ã— and 7.6Ã— speedups, respectively, over the optimized code generated by off-the-shelf SoufflÃ© on SMT-heavy Formulog benchmarks. All in all, using compilation and eager evaluation (as appropriate), Formulog implementations of refinement type checking, bottom-up pointer analysis, and symbolic execution achieve speedups on 20 out of 23 benchmarks over previously published, hand-tuned analyses written in F | E81: Datalog, Formulog, SMT solving, compilation, parallel evaluation | F81: 900 - No match | G81: 900 - No match | H81: [] | I81: [] | J81: =+LEN(H81) -> 2 | K81: =+LEN(I81) -> 2
A82: /doi/10.1145/3597065.3597450 | B82: ACM | C82: A Performance Evaluation Software Platform for 5G-based Integrated Sensing and Communication | D82: Integrated sensing and communication (ISAC) will play a pivotal role in the fifth-generation-advanced (5G-A) and sixth-generation (6G) multi-functional networks for its promising potential to bridge between real and digital worlds via the Metaverse. Realizing sensing functions based on the existing 5G network is the primary concern of the communication-centric ISAC technical route. However, the simulation methods verifying multi-node communication and sensing functions are absent nowadays. Therefore, in this paper, a software platform aimed at evaluating miscellaneous performances of the 5G-based ISAC system is introduced. The gNB-based ISAC scenario, the platform architecture design, 5G time-frequency resources, and the 3D-FFT signal processing algorithm are briefly illustrated. System-level performance evaluation results serve as examples of the platform capacities, including the feasibility of certain 5G reference signals to conduct sensing services, and the performance trade-off between communication and sensing using certain reference signals. | E82: integrated sensing and communication, metaverse, software platform, system-level performance evaluation | F82: 900 - No match | G82: 900 - No match | H82: [] | I82: [] | J82: =+LEN(H82) -> 2 | K82: =+LEN(I82) -> 2
A83: /doi/10.1145/3469877.3490614 | B83: ACM | C83: Inter-modality Discordance for Multimodal Fake News Detection | D83: The paradigm shift in the consumption of news via online platforms has cultivated the growth of digital journalism. Contrary to traditional media, lowering entry barriers and enabling everyone to be part of content creation have disabled the concept of centralized gatekeeping in digital journalism. This in turn has triggered the production of fake news. Current studies have made a significant effort towards multimodal fake news detection with less emphasis on exploring the discordance between the different multimedia present in a news article. We hypothesize that fabrication of either modality will lead to dissonance between the modalities, and resulting in misrepresented, misinterpreted and misleading news. In this paper, we inspect the authenticity of news coming from online media outlets by exploiting relationship (discordance) between the textual and multiple visual cues. We develop an inter-modality discordance based fake news detection framework to achieve the goal. The modal-specific discriminative features are learned, employing the cross-entropy loss and a modified version of contrastive loss that explores the inter-modality discordance. To the best of our knowledge, this is the first work that leverages information from different components of the news article (i.e., headline, body, and multiple images) for multimodal fake news detection. We conduct extensive experiments on the real-world datasets to show that our approach outperforms the state-of-the-art by an average F1-score of 6.3%. | E83: Contrastive Loss, Inter-modality Discordance, Metric learning, Multimodal Fake News, Multitask learning | F83: 900 - No match | G83: 900 - No match | H83: [] | I83: [] | J83: =+LEN(H83) -> 2 | K83: =+LEN(I83) -> 2
A84: /doi/10.1145/3583780.3614846 | B84: ACM | C84: Disentangled Interest importance aware Knowledge Graph Neural Network for Fund Recommendation | D84: At present, people are gradually becoming aware of financial management and thus fund recommendation attracts more and more attention to help them find suitable funds quickly. As a user usually takes many factors (e.g., fund theme, fund manager) into account when investing a fund and the fund usually consists of a substantial collection of investments, effectively modeling multi-interest representations is more crucial for personalized fund recommendation than the traditional goods recommendation. However, existing multi-interest methods are largely sub-optimal for fund recommendation, since they ignore financial domain knowledge and diverse fund investment intentions. In this work, we propose a Disentangled Interest importance aware Knowledge Graph Neural Network (DIKGNN) for personalized fund recommendation on FinTech platforms. In particular, we restrict the multiple intent spaces by introducing the attribute nodes from the fund knowledge graph as the minimum intent modeling unit to utilize financial domain knowledge and provide interpretability. In the intent space, we define disentangled intent representations, equipped with intent importance distributions to describe the diverse fund investment intentions. Then we design a new neighbor aggregation mechanism with the learned intent importance distribution upon the interaction graph and knowledge graph to collect multi-intent information. Furthermore, we leverage micro independence and macro balance constraints on the representations and distributions respectively to encourage intent independence and diversity. The extensive experiments on public recommendation benchmarks demonstrate that DIKGNN can achieve substantial improvement over state-of-the-art methods. Our proposed model is also evaluated over one real-world industrial fund dataset from a FinTech platform and has been deployed online. | E84: disentangled, fund recommendation, graph neural network, knowledge graph | F84: 900 - No match | G84: 900 - No match | H84: [] | I84: [] | J84: =+LEN(H84) -> 2 | K84: =+LEN(I84) -> 2
A85: /doi/10.1145/3264869.3264872 | B85: ACM | C85: Generation Method for Immersive Bullet-Time Video Using an Omnidirectional Camera in VR Platform | D85: This paper proposes a generation method of immersive bullet-time video that continuously switches the images captured by multi-viewpoint omnidirectional cameras arranged around the subject. In ordinary bullet-time processing, it is possible to observe a point of interest (POI) at the same screen position by applying projective transformation to captured multi-viewpoint images. However, the observable area is limited by the field of view of the capturing cameras. Thus, a blank region is added to the displayed image, depending on the spatial relationship between the POI and the capturing camera. This seriously harms image quality (i.e., immersiveness). We solve this problem by applying omnidirectional cameras to bullet-time video production. Furthermore, by using the virtual reality platform for calibration of multi-viewpoint omnidirectional cameras and display of bullet-time video, fast and simple processing can be realised. | E85: bullet-time video, camera calibration, multi-viewpoint shooting, omnidirectional camera, vr platform | F85: 1 - Complete terms | G85: 900 - No match | H85: ['virtual reality', 'virtual environment', 'VR'] | I85: [] | J85: =+LEN(H85) -> 48 | K85: =+LEN(I85) -> 2
A86: /doi/10.1145/3357384.3357823 | B86: ACM | C86: Multi-task based Sales Predictions for Online Promotions | D86: The e-commerce era is witnessing a rapid development of various annual online promotions, such as Black Friday, Cyber Monday, and Alibaba's 11.11, etc. S ales P redictions for O nline P romotions (SPOP) are a set of sales related forecasts for the promotion day, including gross merchandise volume, sales volume, best selling products, etc. SPOP is highly important for e-commerce platforms to efficiently organize merchandise and maximize business values. However, sales patterns during the promotions are varied according to different scenarios, each model of which is designed with different features, static or dynamic, for one task in particular. Therefore, several models are proposed with part of features that are possibly beneficial to other tasks, which indicates the universal representation for the items needs to be learned across different promotion scenarios. To address this problem, this paper proposes a D eep I tem N etwork for O nline P romotions (DINOP). In DINOP, we design a novel T arget U sers C ontrolled G ated R ecurrent U nit (TUC-GRU) structure for dynamic features, and provide a new attention mechanism introducing static users profiles. In contrast to traditional prediction models, the network we proposed can effectively and efficiently learn universal item representation by incorporating users' properties as controllers. Furthermore, it can successfully discover the static and dynamic features guided by the multi-task learning, and is easily extended to other sales related prediction problems without retraining. Empirical results show that performance of DINOP in the real data set of Alibaba's Global Shopping Festival is superior to other state-of-the-arts practical methodologies in terms of the convergence rate and prediction accuracy. | E86: multi-task learning, online promotion, representation learning, sales prediction | F86: 900 - No match | G86: 900 - No match | H86: [] | I86: [] | J86: =+LEN(H86) -> 2 | K86: =+LEN(I86) -> 2
A87: /doi/10.1145/3636534.3701549 | B87: ACM | C87: DRAGON: A DRL-based MIMO Layer and MCS Adapter in Open RAN 5G Networks | D87: In the rapidly evolving field of wireless communication, Multiple Input Multiple Output (MIMO) networks have emerged as a pivotal technology, offering enhanced data rates and spectral efficiency by leveraging multiple antennas at both the transmitter and receiver. The introduction of Open Radio Access Network (O-RAN) architecture has further revolutionized this domain, enabling greater flexibility, scalability, and interoperability through its open interfaces and software-defined approach. This paper presents DRAGON, a novel Deep Reinforcement Learning (DRL)-based framework for joint Layer and Modulation and Coding Scheme (MCS) selection, tailored for downlink single-user MIMO networks under the O-RAN framework. Our approach is designed to be highly scalable, capable of efficiently managing a large number of configuration options in one-shot prediction, including up to 25 MCS and 4 layer choices. The proposed solution has been rigorously evaluated using an O-RAN-based simulation environment, demonstrating up to an 18% performance improvement over the state-of-the-art (SOTA) methods and achieving a best throughput of 87.4% when compared to the collected ground-truth dataset. Furthermore, our method supports real-time prediction, making it viable for practical deployment. In addition to these advancements, we explore the potential integration of our DRL-based solution with real-world platforms and discuss the extension of our approach to handle multi-user (MU) MIMO scenarios, paving the way for broader applications in next-generation wireless networks. | E87: open RAN, reinforcement learning, modulation and code scheme, MIMO | F87: 900 - No match | G87: 2 - Complete terms | H87: [] | I87: ['multi-user'] | J87: =+LEN(H87) -> 2 | K87: =+LEN(I87) -> 14
A88: /doi/10.1145/3383313.3412251 | B88: ACM | C88: Towards Safety and Sustainability: Designing Local Recommendations for Post-pandemic World | D88: The COVID-19 pandemic has made it paramount to maintain social distance to limit the viral transmission probability. At the same time, local businesses (e.g., restaurants, cafes, stores, malls) need to operate to ensure their economic sustainability. Considering the wide usage of local recommendation platforms like Google Local and Yelp by customers to choose local businesses, we propose to design local recommendation systems which can help in achieving both safety and sustainability goals. Our investigation of existing local recommendation systems shows that they can lead to overcrowding at some businesses compromising customer safety, and very low footfall at other places threatening their economic sustainability. On the other hand, naive ways of ensuring safety and sustainability can cause significant loss in recommendation utility for the customers. Thus, we formally express the problem as a multi-objective optimization problem and solve by innovatively mapping it to a bipartite matching problem with polynomial time solutions. Extensive experiments over multiple real-world datasets reveal the efficacy of our approach along with the three-way control over sustainability, safety, and utility goals. | E88: Bipartite Matching, COVID-19, Google Local, Local Recommendation, Safety, Social Distancing, Sustainability, Yelp | F88: 900 - No match | G88: 900 - No match | H88: [] | I88: [] | J88: =+LEN(H88) -> 2 | K88: =+LEN(I88) -> 2
A89: /doi/10.1145/3534678.3539055 | B89: ACM | C89: An Online Multi-task Learning Framework for Google Feed Ads Auction Models | D89: In this paper, we introduce a large scale online multi-task deep learning framework for modeling multiple feed ads auction prediction tasks on an industry-scale feed ads recommendation platform. Multiple prediction tasks are combined into one single model which is continuously trained on real time new ads data. Multi-tasking ads auction models in real-time faces many real-world challenges. For example, each task may be trained on different set of training data; the labels of different tasks may have different arrival time due to label delay; different tasks will interact with each other; combining the losses of each task is non-trivial. We tackle these challenges using practical and novel techniques such as multi-stage training for handling label delay, Multi-gate Mixture-of-Experts (MMoE) to optimize model interaction and an auto-parameter learning algorithm to optimize the loss weights of different tasks. We demonstrate that our proposed techniques can lead to quality improvements and substantial resource saving compared to modeling each single task independently. | E89: computational advertising, multi-task learning, online advertising, recommender systems | F89: 900 - No match | G89: 900 - No match | H89: [] | I89: [] | J89: =+LEN(H89) -> 2 | K89: =+LEN(I89) -> 2
A90: /doi/10.1145/3242153.3242157 | B90: ACM | C90: Real-time ETL in Striim | D90: In the new digital economy, on demand access of real time enterprise data is critical to modernize cross organizational, cross partner, and online consumer functions. In addition to on premise legacy data, enterprises are producing an enormous amount of real-time data through new hybrid cloud applications; these event streams need to be collected, transformed and analyzed in real-time to make critical business decision. Traditional Extract-Load-Transform (ETL) processes are no longer sufficient and need to be re-architected to account for streaming, heterogeneity, usability, extensibility (custom processing), and continuous validity. | E90: ETL, Real-time, data validation | F90: 900 - No match | G90: 900 - No match | H90: [] | I90: [] | J90: =+LEN(H90) -> 2 | K90: =+LEN(I90) -> 2
A91: /doi/10.1145/3580305.3599550 | B91: ACM | C91: Who Should Be Given Incentives? Counterfactual Optimal Treatment Regimes Learning for Recommendation | D91: Effective personalized incentives can improve user experience and increase platform revenue, resulting in a win-win situation between users and e-commerce companies. Previous studies have used uplift modeling methods to estimate the conditional average treatment effects of users' incentives, and then placed the incentives by maximizing the sum of estimated treatment effects under a limited budget. However, some users will always buy whether incentives are given or not, and they will actively collect and use incentives if provided, named "Always Buyers". Identifying and predicting these "Always Buyers" and reducing incentive delivery to them can lead to a more rational incentive allocation. In this paper, we first divide users into five strata from an individual counterfactual perspective, and reveal the failure of previous uplift modeling methods to identify and predict the "Always Buyers". Then, we propose principled counterfactual identification and estimation methods and prove their unbiasedness. We further propose a counterfactual entire-space multi-task learning approach to accurately perform personalized incentive policy learning with a limited budget. We also theoretically derive a lower bound on the reward of the learned policy. Extensive experiments are conducted on three real-world datasets with two common incentive scenarios, and the results demonstrate the effectiveness of the proposed approaches. | E91: counterfactual, optimal treatment regime, recommender system. | F91: 900 - No match | G91: 900 - No match | H91: [] | I91: [] | J91: =+LEN(H91) -> 2 | K91: =+LEN(I91) -> 2
A92: /doi/10.1145/3373400.3373402 | B92: ACM | C92: PrVM: a multicore real-time virtualization scheduling framework with probabilistic timing guarantees | D92: We present PrVM, a framework for scheduling real-time VMs on multicore hardware. It addresses the intersection of the following problems: probabilistic real-time scheduling, VM scheduling, and full virtualization. Though each of these problems have been studied, their intersection - motivated by the need to consolidate multiple real-time software stacks, whose applications can be defined via probabilistic timing properties, onto a single embedded platform - is empty. PrVM uses a probabilistic model and timeliness optimality criterion. PrVM schedules VMs as server-like processes, computes time budgets using probabilistic methods, and aggregates task time budgets into VM time budgets. Experimental evaluations, using simulations and a concrete implementation, confirm the framework's effectiveness for synthetic benchmarks and multimedia applications. | F92: 900 - No match | G92: 900 - No match | H92: [] | I92: [] | J92: =+LEN(H92) -> 2 | K92: =+LEN(I92) -> 2
A93: /doi/10.1145/3426425.3426930 | B93: ACM | C93: Annotating executable DSLs with energy estimation formulas | D93: Reducing the energy consumption of a complex, especially cyber-physical, system is a cross-cutting concern through the system layers, and typically requires long feedback loops between experts in several engineering disciplines. Having an immediate automatic estimation of the global system consumption at design-time would significantly accelerate this process, but cross-layer tools are missing in several domains. | E93: cyber-physical systems, energy estimation, xDSL | F93: 900 - No match | G93: 900 - No match | H93: [] | I93: [] | J93: =+LEN(H93) -> 2 | K93: =+LEN(I93) -> 2
A94: /doi/10.1145/2838944.2838949 | B94: ACM | C94: Improving walking ability of children with acquired brain injuries by means of an immersive virtual reality platform | D94: Improving walking ability is one of the main goals of a rehabilitation procedure. New technologies based on Virtual Reality (VR) has been recently flanked standard therapies. In this study, 4 children suffering from acquired brain injury (ABI) underwent a 5 session treatment with the Gait Real-time Analysis Interactive Lab (GRAIL), to improve walking and balance ability. The GRAIL is an instrumented multi-sensor platform based on immersive virtual reality for gait training and rehabilitation in engaging VR environments, which has been included in few studies to evaluate gait patterns in normal and disabled people and to improve gait in adults. Results are promising: improvements were recorded at the ankle level, selectively at the affected side, and at the pelvic level, thus improving the walking pattern symmetry. Small changes were measured at the hip and knee joints, which were already comparable to healthy subjects. These results suggest that a longer intervention may be even more effective. In the next future more children will be enrolled to strongly prove the effectiveness of GRAIL in the rehabilitation of children with ABI. | E94: Immersive virtual reality, acquired brain injury, children, gait rehabilitation | F94: 1 - Complete terms | G94: 900 - No match | H94: ['virtual reality', 'virtual environment', 'VR'] | I94: [] | J94: =+LEN(H94) -> 48 | K94: =+LEN(I94) -> 2
A95: /doi/10.1145/3166227.3166238 | B95: ACM | C95: Real-time network function virtualization with timing interfaces | D95: More and more infrastructure is becoming virtualized. Recently this trend has begun to include network functions - such as firewalls, WAN optimizers, and intrusion prevention systems - that have traditionally been implemented as middleboxes using dedicated hardware. This trend towards network function virtualization (NFV) offers a variety of potential benefits that resemble those of cloud computing, including consolidation, easier management, higher efficiency, and better scalability. However, current cloud technology is not a perfect match for NFV workloads: since the infrastructure is shared, the time it takes for a packet to pass through a particular function is no longer predictable, and can in fact vary considerably. This is causing headaches for operators, who can no longer treat network functions as "bumps in the wire" and must now consider a complex web of possible interactions and cross-talk when operating or diagnosing their systems. | F95: 900 - No match | G95: 900 - No match | H95: [] | I95: [] | J95: =+LEN(H95) -> 2 | K95: =+LEN(I95) -> 2
A96: /doi/10.1109/UCC.2014.38 | B96: ACM | C96: Metaheuristics-Based Planning and Optimization for SLA-Aware Resource Management in PaaS Clouds | D96: The Platform as a Service (PaaS) model of Cloud Computing has emerged as an enabling yet disruptive paradigm for accelerated development of applications on the Cloud. PaaS hides administration complexities of the underlying infrastructure such as the physical or virtual machines. This abstraction is achieved through advanced automation and OS-level multi-tenant containers. However, the on-demand procurement, unpredictable workloads and auto-scaling result in rapid increase and decrease of containers. This causes undesired utilization of Cloud resources and energy wastage that can be avoided with real time planning. Hence, the main challenge of a PaaS Cloud provider is to regularly plan and optimize the placement of containers on Cloud machines. However, the service-driven constraints regarding containers and spatial constraints regarding machines make SLA-aware resource allocation non-trivial. This relatively novel "Service Consolidation" problem is a variant of multi-dimensional bin-packing and hence NP-hard. In this work, we concretely frame this problem by leveraging the definition of Machine Reassignment model proposed by Google for the ROADEF/EURO challenge and characterize it for Open Shift PaaS. We apply Metaheuristic search to discover best (re) allocation solutions on Clouds of varying scales. We compare four state of the art algorithms as problem properties change in datasets and evaluate their performance against a variety of metrics including objective function score, machines used, utilization, resource contention, SLA violations, migrations and energy consumption. Finally, we present a policy-led ranking of solutions to obscure the complexity of individual metrics and decide for the most preferred solution. Hence, we provide valuable insights for SLA-aware resource management in PaaS Clouds. | E96: Cloud Computing, Open Shift, Optimization, PaaS, Resource Allocation, SLA Violations, Service Consolidation, Service Level Agreement (SLA), Service Migration | F96: 900 - No match | G96: 900 - No match | H96: [] | I96: [] | J96: =+LEN(H96) -> 2 | K96: =+LEN(I96) -> 2
A97: /doi/10.1145/3404890 | B97: ACM | C97: Blockchain-enabled Tensor-based Conditional Deep Convolutional GAN for Cyber-physical-Social Systems | D97: Deep learning techniques have shown significant success in cyber-physical-social systems (CPSS). As an instance of deep learning models, generative adversarial nets (GAN) model enables powerful and flexible image augmentation, image generation, and classification, thus can be applied to real-world CPSS settings. GAN model training needs a large collection of cyber-physical-social data originating from various CPSS devices. Numerous prevailing GAN models depend on a tacit assumption that several cyber-physical-social data providers present a reliable source to collect training data, which is seldom the case in real CPSS. The existing GAN models also fail to consider multi-dimensional latent structure. In our work, we put forward a novel blockchain-enabled tensor-based conditional deep convolutional GAN (TCDC-GAN) model for cyber-physical-social systems. The blockchain is employed to develop a decentralized and reliable cyber-physical-social data-sharing platform between numerous cyber-physical-social data providers, such that the training data and the model are documented on a ledger that is distributed. Furthermore, a tensor-based generator and a tensor-based discriminator are well designed by employing the tensor model. The results of extensive simulation experiments show the efficacy of the proposed TCDC-GAN model. Compared with the state-of-the-art models, our model gains superior estimation performance. | E97: Cyber-physical-social systems, deep learning, generative adversarial network, tensor, blockchain | F97: 900 - No match | G97: 900 - No match | H97: [] | I97: [] | J97: =+LEN(H97) -> 2 | K97: =+LEN(I97) -> 2
A98: /doi/10.1145/3402942.3409789 | B98: ACM | C98: Assessing Multiplayer Level Design Using Deep Learning Techniques | D98: This paper proposes a new framework to measure the fairness of asymmetric level-design in multiplayer games. This work achieves real time prediction of the degree to which asymmetric levels are balanced using deep learning. The proposed framework provides both cost and time savings, by removing the requirement of numerous designed levels and the need to gather player data samples. This advancement with the field is possible through the combination of deep reinforcement learning (made accessible to developers with Unityâ€™s ML-Agents framework), and Procedural Content Generation (PCG). The result of this merger is the acquisition of accelerated training data, which is established using parallel simulations. This paper showcases the proposed approach on a simple two player top-down -shooter game implemented using MoreMountains: Top Down Engine an extension to Unity 3D a popular game engine. Levels are generated using the same PCG approaches found in â€™Nuclear Throneâ€™ a popular cross platform Roguelike published by Vlambeer. | E98: Game Balance, Level Design, Procedural Content Generation, Reinforcement Learning | F98: 900 - No match | G98: 1 - Complete terms cross | H98: [] | I98: ['cross platform'] | J98: =+LEN(H98) -> 2 | K98: =+LEN(I98) -> 18
A99: /doi/10.1145/3276799.3276803 | B99: ACM | C99: Mosaic5G: agile and flexible service platforms for 5G research | D99: Network slicing is one of the key enablers to provide the required flexibility and to realize the service-oriented vision toward fifth generation (5G) mobile networks. In that sense, virtualization, softwarization, and disaggregation are core concepts to accommodate the requirements of an end-to-end (E2E) service to be either isolated, shared, or customized. They lay the foundation for a multi-service and multi-tenant architecture, and are realized by applying the principles of software-defined networking (SDN), network function virtualization (NFV), and cloud computing to the mobile networks. Research on these principles requires agile and flexible platforms that offer a wide range of real-world experimentations over different domains to open up innovations in 5G. To this end, we present Mosaic5G, a community-led consortium for sharing platforms, providing a number of software components, namely FlexRAN, LL-MEC, JOX and Store, spanning application, management, control and user plane on top of OpenAirInterface (OAI) platform. Finally, we show several use cases of Mosaic5G corresponding to widely-mentioned 5G research directions. | E99: 5G, network slicing, open-source platforms, service-orientation | F99: 900 - No match | G99: 900 - No match | H99: [] | I99: [] | J99: =+LEN(H99) -> 2 | K99: =+LEN(I99) -> 2
A100: /doi/10.1145/3604280 | B100: ACM | C100: VPRNet: Voxel-based Efficient and Partial-to-Partial Point Cloud Registration on Mobile Devices | D100: With the popularity of embedded devices such as LIDAR sensors and depth cameras, the resulting point clouds become the main data format for representing the 3D world and spawn various smart mobile applications. A key technology for enabling these applications to furnish high-quality services is real-time point cloud registration on mobile devices, which synthesizes a complete model or a large-scale scene from multiple partial scans. It aims to deliver increasing sensing range, faster 3D reconstruction and more robust robot navigation. Unfortunately, the performance of these applications is limited by the scale and partial loss of raw point cloud frame. The existing solutions for point cloud registration are difficult to deploy on mobile devices due to their complex models and assumptions about point cloud pairs with large overlap, which cause significant delay and inaccuracy. This paper proposes VPRNet - the first voxel-based registration solution that can achieve real-time partial-to-partial registration with competitive registration quality while being more advantageous for large-scale point clouds on mobile devices. We conduct real-world experiments and extensive simulations cross various datasets and platforms to validate the efficacy of VPRNet and further compare the performance with state-of-the-art approaches. | E100: large-scale point clouds, mobile computing, partial-to-partial registration | F100: 3 - Modified acrs | G100: 900 - No match | H100: ['LIDAR'] | I100: [] | J100: =+LEN(H100) -> 9 | K100: =+LEN(I100) -> 2
A101: /doi/10.1145/2815317.2815340 | B101: ACM | C101: Performance Evaluation of the VB-TDMA Protocol for Long-term Tracking and Monitoring of Mobile Entities in the Outdoors | D101: The Virtual Beacon-Time Division Multiple Access (VB-TDMA) communication protocol has been proposed in [12] for a growing class of applications which require GPS tracking of autonomous mobile entities in the outdoors, and the long-term continuous monitoring of their contextual information using wireless sensors. Examples include monitoring animal behaviour in their natural habitat over the annual cycle, tracking shipping containers during their life-cycle of transit, loading/unloading and storage, and the handling of high-value packages during transportation. This paper employs simulations to evaluate the network performance of the VB-TDMA communication protocol in a representative scenario involving wild horses attached with collars, each containing a custom-designed platform with a three-axis accelerometer, a GPS module and ancillary electronics and battery, which uploads wirelessly to static base-stations, its position (sensed thrice an hour) and a summary of its activities between uploads. The simulations benefited from movement models derived from real data obtained from a long-term deployment of the collars on wild horses in the Donana National Park in south-west Spain. Comparisons with other MAC protocols have demonstrated the superior performance of the VB-TDMA protocol over a range of metrics for the representative example. An enhanced version of the VB-TDMA protocol - a multi-hop variant - is introduced for low latency requirements and was simulated for an urban scenario of bicycles fitted with sensors for crowd-sourcing spatio-temporal air quality information along the route of travel which is uploaded to the server when within range of static base-stations, for cases where low latency data upload is a requirement to enable access to the latest air quality information. | E101: gps, network performance, simulation, tdma, vb-tdma, virtual beacon, wildlife tracking and monitoring, wireless sensor networks | F101: 900 - No match | G101: 900 - No match | H101: [] | I101: [] | J101: =+LEN(H101) -> 2 | K101: =+LEN(I101) -> 2
A102: /doi/10.1145/3477314.3507030 | B102: ACM | C102: Simulating execution time and power consumption of real-time tasks on embedded platforms | D102: In this paper, we present PARTSim, an open-source power/thermal-aware simulator for embedded real-time systems. This tool is a fork of the well-known RTSim simulator, which can simulate the timing behavior of a set of real-time tasks with various characteristics when running on a multi-processor platform in presence of a number of real-time scheduling policies. PARTSim extends the functionality of RTSim by introducing support for power-aware embedded platforms exhibiting frequency scaling and specific architectural patterns like the ARM big.LITTLE and DynamIQ ones. Experimental results that compare simulated data against execution profiles collected on real platforms show a simulation error under 10 % for both execution time and power consumption at 90th percentile when simulating the effects of DVFS. | E102: ARM big.LITTLE, DVFS, heterogeneous embedded systems, real-time systems, scheduling, simulation | F102: 3 - Modified acrs | G102: 900 - No match | H102: ['ARM'] | I102: [] | J102: =+LEN(H102) -> 7 | K102: =+LEN(I102) -> 2
A103: /doi/10.1145/2800835.2804401 | B103: ACM | C103: Keeping it private: an augmented reality approach to citizen participation with public displays | D103: With the availability of displays in public space increasing, they have been proposed and studied as platform for civic engagement. Due to their situated nature, public displays have the potential to enable a larger cross-section of the public to participate in community consultation processes, compared to focus groups or online surveys. Previous research has investigated a range of interaction methods for enabling this form of citizen participation with public displays. Through an analysis of related work we identified four main categories of interaction methods: remote indirect, kiosk, mid-air gestural and mobile. In this paper we propose a formerly introduced interaction method, based upon mobile augmented reality, which promises to enable pervasive participation by making interactions more private and simultaneous, through a familiar and convenient interface. | E103: civic computing, community engagement, mobile augmented reality, pervasive displays, pervasive participation | F103: 1 - Complete terms | G103: 900 - No match | H103: ['augmented reality'] | I103: [] | J103: =+LEN(H103) -> 21 | K103: =+LEN(I103) -> 2
A104: /doi/10.1145/3366423.3380191 | B104: ACM | C104: Learning to Respond with Stickers: A Framework of Unifying Multi-Modality in Multi-Turn Dialog | D104: Stickers with vivid and engaging expressions are becoming increasingly popular in online messaging apps, and some works are dedicated to automatically select sticker response by matching text labels of stickers with previous utterances. However, due to their large quantities, it is impractical to require text labels for the all stickers. Hence, in this paper, we propose to recommend an appropriate sticker to user based on multi-turn dialog context history without any external labels. Two main challenges are confronted in this task. One is to learn semantic meaning of stickers without corresponding text labels. Another challenge is to jointly model the candidate sticker with the multi-turn dialog context. To tackle these challenges, we propose a sticker response selector (SRS) model. Specifically, SRS first employs a convolutional based sticker image encoder and a self-attention based multi-turn dialog encoder to obtain the representation of stickers and utterances. Next, deep interaction network is proposed to conduct deep matching between the sticker with each utterance in the dialog history. SRS then learns the short-term and long-term dependency between all interaction results by a fusion network to output the the final matching score. To evaluate our proposed method, we collect a large-scale real-world dialog dataset with stickers from one of the most popular online chatting platform. Extensive experiments conducted on this dataset show that our model achieves the state-of-the-art performance for all commonly-used metrics. Experiments also verify the effectiveness of each component of SRS. To facilitate further research in sticker selection field, we release this dataset of 340K multi-turn dialog and sticker pairs1. | E104: multi-turn dialog, online chatting, sticker selection | F104: 900 - No match | G104: 900 - No match | H104: [] | I104: [] | J104: =+LEN(H104) -> 2 | K104: =+LEN(I104) -> 2
A105: /doi/10.5555/2755753.2755883 | B105: ACM | C105: MPIOV: scaling hardware-based I/O virtualization for mixed-criticality embedded real-time systems using non transparent bridges to (multi-core) multi-processor systems | D105: Safety-critical systems consolidating multiple functionalities of different criticality (so-called mixed-criticality systems) require separation between these functionalities to assure safety and security properties. Performance-hungry and safety-critical applications (like a radar processing system steering an autonomous flying aircraft) may demand an embedded high-performance computing cluster of more than one (multi-core) processor. This paper presents the | E105: IOMMU, IOMPU, hardware-based I/O virtualization, mixed-criticality systems, multi-core, multi-processor, non-transparent bridge (NTB), real-time embedded systems, spatial separation | F105: 900 - No match | G105: 900 - No match | H105: [] | I105: [] | J105: =+LEN(H105) -> 2 | K105: =+LEN(I105) -> 2
A106: /doi/10.1145/3077136.3080771 | B106: ACM | C106: Item Silk Road: Recommending Items from Information Domains to Social Users | D106: Online platforms can be divided into information-oriented and social-oriented domains. The former refers to forums or E-commerce sites that emphasize user-item interactions, like Trip.com and Amazon; whereas the latter refers to social networking services (SNSs) that have rich user-user connections, such as Facebook and Twitter. Despite their heterogeneity, these two domains can be bridged by a few overlapping users, dubbed as | E106: cross-domain recommendation, deep collaborative filtering, deep learning, neural network | F106: 900 - No match | G106: 2 - Complete terms | H106: [] | I106: ['collaborative'] | J106: =+LEN(H106) -> 2 | K106: =+LEN(I106) -> 17
A107: /doi/10.1145/3589334.3645324 | B107: ACM | C107: A Data-Centric Multi-Objective Learning Framework for Responsible Recommendation Systems | D107: Recommendation systems guide users in locating their desired information within extensive content repositories. Usually, a recommendation model is optimized to enhance accuracy metrics from a user utility standpoint, such as click-through rate or matching relevance. However, a responsible industrial recommendation model must address not only user utility (responsibility to users) but also other objectives, including increasing platform revenue (responsibility to platforms), ensuring fairness (responsibility to content creators), and maintaining unbiasedness (responsibility to long-term healthy development). Multi-objective learning is a promising approach for achieving responsible recommendation models. Nevertheless, current methods encounter two challenges: difficulty in scaling to heterogeneous objectives within a unified framework, and inadequate controllability over objective priority during optimization, leading to uncontrollable solutions. | E107: data sampling, multi-objective learning, recommender system | F107: 900 - No match | G107: 900 - No match | H107: [] | I107: [] | J107: =+LEN(H107) -> 2 | K107: =+LEN(I107) -> 2
... A114: /doi/10.1145/3640457.3688101 | B114: ACM | C114: Touch the Core: Exploring Task Dependence Among Hybrid Targets for Recommendation | D114: As user behaviors become complicated on business platforms, online recommendations focus more on how to touch the core conversions, which are highly related to the interests of platforms. These core conversions are usually continuous targets, such as watch time, revenue, and so on, whose predictions can be enhanced by previous discrete conversion actions. Therefore, multi-task learning (MTL) can be adopted as the paradigm to learn these hybrid targets. However, existing works mainly emphasize investigating the sequential dependence among discrete conversion actions, which neglects the complexity of dependence between discrete conversions and the final continuous conversion. Moreover, simultaneously optimizing hybrid tasks with stronger task dependence will suffer from volatile issues where the core regression task might have a larger influence on other tasks. In this paper, we study the MTL problem with hybrid targets for the first time and propose the model named Hybrid Targets Learning Network (HTLNet) to explore task dependence and enhance optimization. Specifically, we introduce label embedding for each task to explicitly transfer the label information among these tasks, which can effectively explore logical task dependence. We also further design the gradient adjustment regime between the final regression task and other classification tasks to enhance the optimization. Extensive experiments on two offline public datasets and one real-world industrial dataset are conducted to validate the effectiveness of HTLNet. Moreover, online A/B tests on the financial recommender system also show that our model has improved significantly. Our implementation is available here1. | E114: Hybrid Targets, Multi-task Learning, Recommendation, Task Dependence | F114: 900 - No match | G114: 900 - No match | H114: [] | I114: [] | J114: =+LEN(H114) -> 2 | K114: =+LEN(I114) -> 2
A115: /doi/10.5555/2616606.2616798 | B115: ACM | C115: Tightly-coupled hardware support to dynamic parallelism acceleration in embedded shared memory clusters | D115: Modern designs for embedded systems are increasingly embracing cluster-based architectures, where small sets of cores communicate through tightly-coupled shared memory banks and high-performance interconnections. At the same time, the complexity of modern applications requires new programming abstractions to exploit dynamic and/or irregular parallelism on such platforms. Supporting dynamic parallelism in systems which i) are resource-constrained and ii) run applications with small units of work calls for a runtime environment which has minimal overhead for the scheduling of parallel tasks. In this work, we study the major sources of overhead in the implementation of OpenMP dynamic loops, sections and tasks, and propose a hardware implementation of a generic Scheduling Engine (HWSE) which fits the semantics of the three constructs. The HWSE is designed as a tightly-coupled block to the PEs within a multi-core cluster, communicating through a shared-memory interface. This allows very fast programming and synchronization with the controlling PEs, fundamental to achieving fast dynamic scheduling, and ultimately to enable fine-grained parallelism. We prove the effectiveness of our solutions with real applications and synthetic benchmarks, using a cycle-accurate virtual platform. | F115: 900 - No match | G115: 900 - No match | H115: [] | I115: [] | J115: =+LEN(H115) -> 2 | K115: =+LEN(I115) -> 2
...

Sheet Sheet1
A1: Category technology | B1: Subcategory of interest | C1: Marked as included
A2: 1 - Complete terms | B2: 1 - Complete terms cross | C2: x | D2: =+COUNTIFS(output_file_it3!$F$2:$F$17170,A2,output_file_it3!$G$2:$G$17170,B2) -> 165 | E2: =+D2/$D$18 -> 0.065947242
A3: 1 - Complete terms | B3: 2 - Complete terms | D3: =+COUNTIFS(output_file_it3!$F$2:$F$17170,A3,output_file_it3!$G$2:$G$17170,B3) -> 123 | E3: =+D3/$D$18 -> 0.049160671
A4: 1 - Complete terms | B4: 3 - Regex terms | D4: =+COUNTIFS(output_file_it3!$F$2:$F$17170,A4,output_file_it3!$G$2:$G$17170,B4) -> 11 | E4: =+D4/$D$18 -> 0.0043964828 | H4: Papers of iterest | I4: =+SUMIFS($D$2:$D$17,$C$2:$C$17,"x") -> 220
A5: 1 - Complete terms | B5: 900 - No match | D5: =+COUNTIFS(output_file_it3!$F$2:$F$17170,A5,output_file_it3!$G$2:$G$17170,B5) -> 470 | E5: =+D5/$D$18 -> 0.18784972 | I5: =+I4/D18 -> 0.087929656
A6: 2 - Complete acrs | B6: 1 - Complete terms cross | C6: x | D6: =+COUNTIFS(output_file_it3!$F$2:$F$17170,A6,output_file_it3!$G$2:$G$17170,B6) -> 6 | E6: =+D6/$D$18 -> 0.0023980815
A7: 2 - Complete acrs | B7: 2 - Complete terms | D7: =+COUNTIFS(output_file_it3!$F$2:$F$17170,A7,output_file_it3!$G$2:$G$17170,B7) -> 6 | E7: =+D7/$D$18 -> 0.0023980815
A8: 2 - Complete acrs | B8: 3 - Regex terms | D8: =+COUNTIFS(output_file_it3!$F$2:$F$17170,A8,output_file_it3!$G$2:$G$17170,B8) -> 1 | E8: =+D8/$D$18 -> 0.00039968026
A9: 2 - Complete acrs | B9: 900 - No match | D9: =+COUNTIFS(output_file_it3!$F$2:$F$17170,A9,output_file_it3!$G$2:$G$17170,B9) -> 31 | E9: =+D9/$D$18 -> 0.012390088
A10: 3 - Modified acrs | B10: 1 - Complete terms cross | C10: x | D10: =+COUNTIFS(output_file_it3!$F$2:$F$17170,A10,output_file_it3!$G$2:$G$17170,B10) -> 49 | E10: =+D10/$D$18 -> 0.019584333
A11: 3 - Modified acrs | B11: 2 - Complete terms | D11: =+COUNTIFS(output_file_it3!$F$2:$F$17170,A11,output_file_it3!$G$2:$G$17170,B11) -> 6 | E11: =+D11/$D$18 -> 0.0023980815
A12: 3 - Modified acrs | B12: 3 - Regex terms | D12: =+COUNTIFS(output_file_it3!$F$2:$F$17170,A12,output_file_it3!$G$2:$G$17170,B12) -> 0 | E12: =+D12/$D$18 -> 0
A13: 3 - Modified acrs | B13: 900 - No match | D13: =+COUNTIFS(output_file_it3!$F$2:$F$17170,A13,output_file_it3!$G$2:$G$17170,B13) -> 103 | E13: =+D13/$D$18 -> 0.041167066
A14: 900 - No match | B14: 1 - Complete terms cross | D14: =+COUNTIFS(output_file_it3!$F$2:$F$17170,A14,output_file_it3!$G$2:$G$17170,B14) -> 293 | E14: =+D14/$D$18 -> 0.11710631
A15: 900 - No match | B15: 2 - Complete terms | D15: =+COUNTIFS(output_file_it3!$F$2:$F$17170,A15,output_file_it3!$G$2:$G$17170,B15) -> 96 | E15: =+D15/$D$18 -> 0.038369305
A16: 900 - No match | B16: 3 - Regex terms | D16: =+COUNTIFS(output_file_it3!$F$2:$F$17170,A16,output_file_it3!$G$2:$G$17170,B16) -> 1 | E16: =+D16/$D$18 -> 0.00039968026
A17: 900 - No match | B17: 900 - No match | D17: =+COUNTIFS(output_file_it3!$F$2:$F$17170,A17,output_file_it3!$G$2:$G$17170,B17) -> 1141 | E17: =+D17/$D$18 -> 0.45603517
B18: TOTAL | D18: =+SUM(D2:D17) -> 2502
